Workbook

Sheet {worksheet}
A1: 2026-07-09 16:30:22
A2: No. | B2: 거래처 관리코드 | C2: Site | D2: 창고 | E2: 출고일 | F2: 등록자 | G2: 거래처 | H2: 거래처 약칭 | I2: 국가 | J2: Biz Type | K2: 상품코드 | L2: 상품명 | M2: 브랜드 | N2: Curr | O2: 수량 | P2: 판매단가 | Q2: 금액 | R2: VAT | S2: 환산금액 | T2: 평균단가 | U2: 마진율 적용 | V2: 판매이익 | W2: 사용 목적 | X2: % | Y2: Invoice No | AA2: Month | AB2: Period | AC2: Revenue_KRW | AD2: Qty_num | AE2: Profit_KRW | AF2: Type
A3: 1 | B3: 06312 | C3: KR | D3: KR-W | E3: 2025-09-05 | F3: diane | G3: MOARS | I3: Netherlands The | J3: KR-OVERSEAS | K3: PYS13-A | L3: (변경예정) 얼티밋 진정 솔루션 앰플 30ml | M3: 편강율 | N3: USD | O3: 4,050 | P3: 0.00 | Q3: 0.00 | R3: 0.00 | S3: 0.00 | T3: 0.00 | U3: 0.00 | V3: 0.00 | W3: 상품 샘플링 (견본,무상증정) | X3: 0.0 | Y3: IN00369756 | AA3: =LEFT(E3,7) -> 2025-09 | AB3: =IF(AND($AA3>="2025-01",$AA3<="2025-06"),"H1_2025",IF(AND($AA3>="2026-01",$AA3<="2026-06"),"H1_2026","")) | AC3: =IFERROR(VALUE(SUBSTITUTE(S3,",","")),0) -> 0 | AD3: =IFERROR(VALUE(SUBSTITUTE(O3,",","")),0) -> 4050 | AE3: =IFERROR(VALUE(SUBSTITUTE(V3,",","")),0) -> 0 | AF3: =IF(ISNUMBER(SEARCH("FOC",W3)),"FOC",IF(ISNUMBER(SEARCH("샘플",W3)),"Sample","Paid")) -> Sample
A4: 2 | B4: 06312 | C4: KR | D4: KR-W | E4: 2025-06-19 | F4: diane | G4: MOARS | I4: Netherlands The | J4: KR-OVERSEAS | K4: PRS02-CSU | L4: (통합) 원더 릴리프 센텔라 세럼 언센티드 60ml | M4: 퓨리토 서울 | N4: USD | O4: 11 | P4: 0.00 | Q4: 0.00 | R4: 0.00 | S4: 0.00 | T4: 0.00 | U4: 0.00 | V4: 0.00 | W4: 상품 샘플링 (견본,무상증정) | X4: 0.0 | Y4: IN00349310 | AA4: =LEFT(E4,7) -> 2025-06 | AB4: =IF(AND($AA4>="2025-01",$AA4<="2025-06"),"H1_2025",IF(AND($AA4>="2026-01",$AA4<="2026-06"),"H1_2026","")) -> H1_2025 | AC4: =IFERROR(VALUE(SUBSTITUTE(S4,",","")),0) -> 0 | AD4: =IFERROR(VALUE(SUBSTITUTE(O4,",","")),0) -> 11 | AE4: =IFERROR(VALUE(SUBSTITUTE(V4,",","")),0) -> 0 | AF4: =IF(ISNUMBER(SEARCH("FOC",W4)),"FOC",IF(ISNUMBER(SEARCH("샘플",W4)),"Sample","Paid")) -> Sample
A5: 3 | B5: 06312 | C5: KR | D5: KR-W | E5: 2025-06-19 | F5: diane | G5: MOARS | I5: Netherlands The | J5: KR-OVERSEAS | K5: PRS04-CREU | L5: (통합) 마이티 밤부 판테놀 크림 100ml | M5: 퓨리토 서울 | N5: USD | O5: 11 | P5: 0.00 | Q5: 0.00 | R5: 0.00 | S5: 0.00 | T5: 0.00 | U5: 0.00 | V5: 0.00 | W5: 상품 샘플링 (견본,무상증정) | X5: 0.0 | Y5: IN00349310 | AA5: =LEFT(E5,7) -> 2025-06 | AB5: =IF(AND($AA5>="2025-01",$AA5<="2025-06"),"H1_2025",IF(AND($AA5>="2026-01",$AA5<="2026-06"),"H1_2026","")) -> H1_2025 | AC5: =IFERROR(VALUE(SUBSTITUTE(S5,",","")),0) -> 0 | AD5: =IFERROR(VALUE(SUBSTITUTE(O5,",","")),0) -> 11 | AE5: =IFERROR(VALUE(SUBSTITUTE(V5,",","")),0) -> 0 | AF5: =IF(ISNUMBER(SEARCH("FOC",W5)),"FOC",IF(ISNUMBER(SEARCH("샘플",W5)),"Sample","Paid")) -> Sample
A6: 4 | B6: 06312 | C6: KR | D6: KR-W | E6: 2025-06-19 | F6: diane | G6: MOARS | I6: Netherlands The | J6: KR-OVERSEAS | K6: PRS04-SETM | L6: (미조립) 세일즈 PR 박스 | M6: 퓨리토 서울 | N6: USD | O6: 11 | P6: 0.00 | Q6: 0.00 | R6: 0.00 | S6: 0.00 | T6: 0.00 | U6: 0.00 | V6: 0.00 | W6: 상품 샘플링 (견본,무상증정) | X6: 0.0 | Y6: IN00349310 | AA6: =LEFT(E6,7) -> 2025-06 | AB6: =IF(AND($AA6>="2025-01",$AA6<="2025-06"),"H1_2025",IF(AND($AA6>="2026-01",$AA6<="2026-06"),"H1_2026","")) -> H1_2025 | AC6: =IFERROR(VALUE(SUBSTITUTE(S6,",","")),0) -> 0 | AD6: =IFERROR(VALUE(SUBSTITUTE(O6,",","")),0) -> 11 | AE6: =IFERROR(VALUE(SUBSTITUTE(V6,",","")),0) -> 0 | AF6: =IF(ISNUMBER(SEARCH("FOC",W6)),"FOC",IF(ISNUMBER(SEARCH("샘플",W6)),"Sample","Paid")) -> Sample
A7: 5 | B7: 06312 | C7: KR | D7: KR-W | E7: 2025-06-19 | F7: diane | G7: MOARS | I7: Netherlands The | J7: KR-OVERSEAS | K7: PRS07-GELR | L7: (Renewal/통합) 오트 인 카밍 젤 크림 100ml | M7: 퓨리토 서울 | N7: USD | O7: 11 | P7: 0.00 | Q7: 0.00 | R7: 0.00 | S7: 0.00 | T7: 0.00 | U7: 0.00 | V7: 0.00 | W7: 상품 샘플링 (견본,무상증정) | X7: 0.0 | Y7: IN00349310 | AA7: =LEFT(E7,7) -> 2025-06 | AB7: =IF(AND($AA7>="2025-01",$AA7<="2025-06"),"H1_2025",IF(AND($AA7>="2026-01",$AA7<="2026-06"),"H1_2026","")) -> H1_2025 | AC7: =IFERROR(VALUE(SUBSTITUTE(S7,",","")),0) -> 0 | AD7: =IFERROR(VALUE(SUBSTITUTE(O7,",","")),0) -> 11 | AE7: =IFERROR(VALUE(SUBSTITUTE(V7,",","")),0) -> 0 | AF7: =IF(ISNUMBER(SEARCH("FOC",W7)),"FOC",IF(ISNUMBER(SEARCH("샘플",W7)),"Sample","Paid")) -> Sample
A8: 6 | B8: 06312 | C8: KR | D8: KR-W | E8: 2025-06-19 | F8: diane | G8: MOARS | I8: Netherlands The | J8: KR-OVERSEAS | K8: PRSM13-SC | L8: (PRSM13-SCREU) 데일리 소프트 터치 선크림 60ml | M8: 퓨리토 서울 | N8: USD | O8: 11 | P8: 0.00 | Q8: 0.00 | R8: 0.00 | S8: 0.00 | T8: 0.00 | U8: 0.00 | V8: 0.00 | W8: 상품 샘플링 (견본,무상증정) | X8: 0.0 | Y8: IN00349310 | AA8: =LEFT(E8,7) -> 2025-06 | AB8: =IF(AND($AA8>="2025-01",$AA8<="2025-06"),"H1_2025",IF(AND($AA8>="2026-01",$AA8<="2026-06"),"H1_2026","")) -> H1_2025 | AC8: =IFERROR(VALUE(SUBSTITUTE(S8,",","")),0) -> 0 | AD8: =IFERROR(VALUE(SUBSTITUTE(O8,",","")),0) -> 11 | AE8: =IFERROR(VALUE(SUBSTITUTE(V8,",","")),0) -> 0 | AF8: =IF(ISNUMBER(SEARCH("FOC",W8)),"FOC",IF(ISNUMBER(SEARCH("샘플",W8)),"Sample","Paid")) -> Sample
A9: 7 | B9: 06312 | C9: KR | D9: KR-W | E9: 2025-06-19 | F9: diane | G9: MOARS | I9: Netherlands The | J9: KR-OVERSEAS | K9: PRSM13-ST | L9: (통합) 데일리 소프트 터치 선스틱 20g | M9: 퓨리토 서울 | N9: USD | O9: 11 | P9: 0.00 | Q9: 0.00 | R9: 0.00 | S9: 0.00 | T9: 0.00 | U9: 0.00 | V9: 0.00 | W9: 상품 샘플링 (견본,무상증정) | X9: 0.0 | Y9: IN00349310 | AA9: =LEFT(E9,7) -> 2025-06 | AB9: =IF(AND($AA9>="2025-01",$AA9<="2025-06"),"H1_2025",IF(AND($AA9>="2026-01",$AA9<="2026-06"),"H1_2026","")) -> H1_2025 | AC9: =IFERROR(VALUE(SUBSTITUTE(S9,",","")),0) -> 0 | AD9: =IFERROR(VALUE(SUBSTITUTE(O9,",","")),0) -> 11 | AE9: =IFERROR(VALUE(SUBSTITUTE(V9,",","")),0) -> 0 | AF9: =IF(ISNUMBER(SEARCH("FOC",W9)),"FOC",IF(ISNUMBER(SEARCH("샘플",W9)),"Sample","Paid")) -> Sample
A10: 8 | B10: 06312 | C10: KR | D10: KR-W | E10: 2025-06-05 | F10: diane | G10: MOARS | I10: Netherlands The | J10: KR-OVERSEAS | K10: HMCM1-DSSM | L10: (리뉴얼) 데일리즘 스머지 스탑 마스카라 컬링 블랙 | M10: 헤이미쉬 | N10: USD | O10: 2,000 | P10: 0.00 | Q10: 0.00 | R10: 0.00 | S10: 0.00 | T10: 36.91 | U10: 73,820.00 | V10: -73,820.00 | W10: 상품 샘플링 (견본,무상증정) | X10: 0.0 | Y10: IN00345465 | AA10: =LEFT(E10,7) -> 2025-06 | AB10: =IF(AND($AA10>="2025-01",$AA10<="2025-06"),"H1_2025",IF(AND($AA10>="2026-01",$AA10<="2026-06"),"H1_2026","")) -> H1_2025 | AC10: =IFERROR(VALUE(SUBSTITUTE(S10,",","")),0) -> 0 | AD10: =IFERROR(VALUE(SUBSTITUTE(O10,",","")),0) -> 2000 | AE10: =IFERROR(VALUE(SUBSTITUTE(V10,",","")),0) -> -73820 | AF10: =IF(ISNUMBER(SEARCH("FOC",W10)),"FOC",IF(ISNUMBER(SEARCH("샘플",W10)),"Sample","Paid")) -> Sample
A11: 9 | B11: 06312 | C11: KR | D11: KR-W | E11: 2025-06-05 | F11: diane | G11: MOARS | I11: Netherlands The | J11: KR-OVERSEAS | K11: PRS04-C | L11: 마이티 밤부 판테놀 크림 100ml | M11: 퓨리토 서울 | N11: USD | O11: 2,000 | P11: 0.00 | Q11: 0.00 | R11: 0.00 | S11: 0.00 | T11: 0.00 | U11: 0.00 | V11: 0.00 | W11: 상품 샘플링 (견본,무상증정) | X11: 0.0 | Y11: IN00345465 | AA11: =LEFT(E11,7) -> 2025-06 | AB11: =IF(AND($AA11>="2025-01",$AA11<="2025-06"),"H1_2025",IF(AND($AA11>="2026-01",$AA11<="2026-06"),"H1_2026","")) -> H1_2025 | AC11: =IFERROR(VALUE(SUBSTITUTE(S11,",","")),0) -> 0 | AD11: =IFERROR(VALUE(SUBSTITUTE(O11,",","")),0) -> 2000 | AE11: =IFERROR(VALUE(SUBSTITUTE(V11,",","")),0) -> 0 | AF11: =IF(ISNUMBER(SEARCH("FOC",W11)),"FOC",IF(ISNUMBER(SEARCH("샘플",W11)),"Sample","Paid")) -> Sample
A12: 10 | B12: 06312 | C12: KR | D12: KR-W | E12: 2025-06-05 | F12: diane | G12: MOARS | I12: Netherlands The | J12: KR-OVERSEAS | K12: PYS01-oilR | L12: [수묵화] 레디언스 페이스 오일 26ml (전: 리뉴얼 오일 26ml) | M12: 편강율 | N12: USD | O12: 2,000 | P12: 0.00 | Q12: 0.00 | R12: 0.00 | S12: 0.00 | T12: 0.00 | U12: 0.00 | V12: 0.00 | W12: 상품 샘플링 (견본,무상증정) | X12: 0.0 | Y12: IN00345465 | AA12: =LEFT(E12,7) -> 2025-06 | AB12: =IF(AND($AA12>="2025-01",$AA12<="2025-06"),"H1_2025",IF(AND($AA12>="2026-01",$AA12<="2026-06"),"H1_2026","")) -> H1_2025 | AC12: =IFERROR(VALUE(SUBSTITUTE(S12,",","")),0) -> 0 | AD12: =IFERROR(VALUE(SUBSTITUTE(O12,",","")),0) -> 2000 | AE12: =IFERROR(VALUE(SUBSTITUTE(V12,",","")),0) -> 0 | AF12: =IF(ISNUMBER(SEARCH("FOC",W12)),"FOC",IF(ISNUMBER(SEARCH("샘플",W12)),"Sample","Paid")) -> Sample
A13: 11 | B13: 06312 | C13: KR | D13: KR-W | E13: 2025-06-05 | F13: diane | G13: MOARS | I13: Netherlands The | J13: KR-OVERSEAS | K13: RLC01-CLRR | L13: *리뉴얼 1025 독도 클렌져_150ml (본품) | M13: 라운드랩 | N13: USD | O13: 2,000 | P13: 0.00 | Q13: 0.00 | R13: 0.00 | S13: 0.00 | T13: 0.00 | U13: 0.00 | V13: 0.00 | W13: 상품 샘플링 (견본,무상증정) | X13: 0.0 | Y13: IN00345465 | AA13: =LEFT(E13,7) -> 2025-06 | AB13: =IF(AND($AA13>="2025-01",$AA13<="2025-06"),"H1_2025",IF(AND($AA13>="2026-01",$AA13<="2026-06"),"H1_2026","")) -> H1_2025 | AC13: =IFERROR(VALUE(SUBSTITUTE(S13,",","")),0) -> 0 | AD13: =IFERROR(VALUE(SUBSTITUTE(O13,",","")),0) -> 2000 | AE13: =IFERROR(VALUE(SUBSTITUTE(V13,",","")),0) -> 0 | AF13: =IF(ISNUMBER(SEARCH("FOC",W13)),"FOC",IF(ISNUMBER(SEARCH("샘플",W13)),"Sample","Paid")) -> Sample
A14: 12 | B14: 06312 | C14: KR | D14: KR-W | E14: 2025-05-26 | F14: diane | G14: MOARS | I14: Netherlands The | J14: KR-OVERSEAS | K14: IUSM07-SCEU | L14: [EU] 센텔라 카밍 데일리 선크림 60ml | M14: 아이유닉 | N14: USD | O14: 1,220 | P14: 0.00 | Q14: 0.00 | R14: 0.00 | S14: 0.00 | T14: 0.00 | U14: 0.00 | V14: 0.00 | W14: 상품 샘플링 (견본,무상증정) | X14: 0.0 | Y14: IN00340192 | AA14: =LEFT(E14,7) -> 2025-05 | AB14: =IF(AND($AA14>="2025-01",$AA14<="2025-06"),"H1_2025",IF(AND($AA14>="2026-01",$AA14<="2026-06"),"H1_2026","")) -> H1_2025 | AC14: =IFERROR(VALUE(SUBSTITUTE(S14,",","")),0) -> 0 | AD14: =IFERROR(VALUE(SUBSTITUTE(O14,",","")),0) -> 1220 | AE14: =IFERROR(VALUE(SUBSTITUTE(V14,",","")),0) -> 0 | AF14: =IF(ISNUMBER(SEARCH("FOC",W14)),"FOC",IF(ISNUMBER(SEARCH("샘플",W14)),"Sample","Paid")) -> Sample
... A16: 14 | B16: 06312 | C16: KR | D16: OPO | E16: 2026-06-18 | F16: minju | G16: MOARS | I16: Netherlands The | J16: KR-OVERSEAS | K16: RjACM01-LEU | L16: [EU] 어드밴스드 PDRN 리쥬비네이팅 립 세럼 10ml | M16: 닥터 리쥬올 | N16: USD | O16: 24 | P16: 0.01 | Q16: 0.24 | R16: 0.00 | S16: 355.51 | T16: 5,600.00 | U16: 134,400.00 | V16: -134,044.49 | W16: FOC (Free of charge, 판매장려금) | X16: -37,704.6 | Y16: IN00447658 | AA16: =LEFT(E16,7) -> 2026-06 | AB16: =IF(AND($AA16>="2025-01",$AA16<="2025-06"),"H1_2025",IF(AND($AA16>="2026-01",$AA16<="2026-06"),"H1_2026","")) -> H1_2026 | AC16: =IFERROR(VALUE(SUBSTITUTE(S16,",","")),0) -> 355.51 | AD16: =IFERROR(VALUE(SUBSTITUTE(O16,",","")),0) -> 24 | AE16: =IFERROR(VALUE(SUBSTITUTE(V16,",","")),0) -> -134044.49 | AF16: =IF(ISNUMBER(SEARCH("FOC",W16)),"FOC",IF(ISNUMBER(SEARCH("샘플",W16)),"Sample","Paid")) -> FOC
A17: 15 | B17: 06312 | C17: KR | D17: OPO | E17: 2026-06-18 | F17: minju | G17: MOARS | I17: Netherlands The | J17: KR-OVERSEAS | K17: RjACM01-LEU | L17: [EU] 어드밴스드 PDRN 리쥬비네이팅 립 세럼 10ml | M17: 닥터 리쥬올 | N17: USD | O17: 240 | P17: 5.83 | Q17: 1,399.20 | R17: 0.00 | S17: 2,072,634.96 | T17: 5,600.00 | U17: 1,344,000.00 | V17: 728,634.96 | X17: 35.2 | Y17: IN00447658 | AA17: =LEFT(E17,7) -> 2026-06 | AB17: =IF(AND($AA17>="2025-01",$AA17<="2025-06"),"H1_2025",IF(AND($AA17>="2026-01",$AA17<="2026-06"),"H1_2026","")) -> H1_2026 | AC17: =IFERROR(VALUE(SUBSTITUTE(S17,",","")),0) -> 2072635 | AD17: =IFERROR(VALUE(SUBSTITUTE(O17,",","")),0) -> 240 | AE17: =IFERROR(VALUE(SUBSTITUTE(V17,",","")),0) -> 728634.96 | AF17: =IF(ISNUMBER(SEARCH("FOC",W17)),"FOC",IF(ISNUMBER(SEARCH("샘플",W17)),"Sample","Paid")) -> Paid
A18: 16 | B18: 06312 | C18: KR | D18: OPO | E18: 2026-06-18 | F18: minju | G18: MOARS | I18: Netherlands The | J18: KR-OVERSEAS | K18: RjAP01-MEU | L18: [EU][4매입] 어드밴스드 PDRN 리쥬비네이팅 마스크 | M18: 닥터 리쥬올 | N18: USD | O18: 4 | P18: 0.01 | Q18: 0.04 | R18: 0.00 | S18: 59.25 | T18: 6,300.00 | U18: 25,200.00 | V18: -25,140.75 | W18: FOC (Free of charge, 판매장려금) | X18: -42,430.2 | Y18: IN00447658 | AA18: =LEFT(E18,7) -> 2026-06 | AB18: =IF(AND($AA18>="2025-01",$AA18<="2025-06"),"H1_2025",IF(AND($AA18>="2026-01",$AA18<="2026-06"),"H1_2026","")) -> H1_2026 | AC18: =IFERROR(VALUE(SUBSTITUTE(S18,",","")),0) -> 59.25 | AD18: =IFERROR(VALUE(SUBSTITUTE(O18,",","")),0) -> 4 | AE18: =IFERROR(VALUE(SUBSTITUTE(V18,",","")),0) -> -25140.75 | AF18: =IF(ISNUMBER(SEARCH("FOC",W18)),"FOC",IF(ISNUMBER(SEARCH("샘플",W18)),"Sample","Paid")) -> FOC
A19: 17 | B19: 06312 | C19: KR | D19: OPO | E19: 2026-06-18 | F19: minju | G19: MOARS | I19: Netherlands The | J19: KR-OVERSEAS | K19: RjAP01-MEU | L19: [EU][4매입] 어드밴스드 PDRN 리쥬비네이팅 마스크 | M19: 닥터 리쥬올 | N19: USD | O19: 40 | P19: 7.29 | Q19: 291.60 | R19: 0.00 | S19: 431,947.08 | T19: 6,300.00 | U19: 252,000.00 | V19: 179,947.08 | X19: 41.7 | Y19: IN00447658 | AA19: =LEFT(E19,7) -> 2026-06 | AB19: =IF(AND($AA19>="2025-01",$AA19<="2025-06"),"H1_2025",IF(AND($AA19>="2026-01",$AA19<="2026-06"),"H1_2026","")) -> H1_2026 | AC19: =IFERROR(VALUE(SUBSTITUTE(S19,",","")),0) -> 431947.08 | AD19: =IFERROR(VALUE(SUBSTITUTE(O19,",","")),0) -> 40 | AE19: =IFERROR(VALUE(SUBSTITUTE(V19,",","")),0) -> 179947.08 | AF19: =IF(ISNUMBER(SEARCH("FOC",W19)),"FOC",IF(ISNUMBER(SEARCH("샘플",W19)),"Sample","Paid")) -> Paid
A20: 18 | B20: 06312 | C20: KR | D20: OPO | E20: 2026-06-18 | F20: minju | G20: MOARS | I20: Netherlands The | J20: KR-OVERSEAS | K20: RjAS01-CLC | L20: 어드벤스드 LC-세라마이드 베리어 크림 50ml | M20: 닥터 리쥬올 | N20: USD | O20: 30 | P20: 0.01 | Q20: 0.30 | R20: 0.00 | S20: 444.39 | T20: 15,000.00 | U20: 450,000.00 | V20: -449,555.61 | W20: FOC (Free of charge, 판매장려금) | X20: -101,162.4 | Y20: IN00447658 | AA20: =LEFT(E20,7) -> 2026-06 | AB20: =IF(AND($AA20>="2025-01",$AA20<="2025-06"),"H1_2025",IF(AND($AA20>="2026-01",$AA20<="2026-06"),"H1_2026","")) -> H1_2026 | AC20: =IFERROR(VALUE(SUBSTITUTE(S20,",","")),0) -> 444.39 | AD20: =IFERROR(VALUE(SUBSTITUTE(O20,",","")),0) -> 30 | AE20: =IFERROR(VALUE(SUBSTITUTE(V20,",","")),0) -> -449555.61 | AF20: =IF(ISNUMBER(SEARCH("FOC",W20)),"FOC",IF(ISNUMBER(SEARCH("샘플",W20)),"Sample","Paid")) -> FOC
A21: 19 | B21: 06312 | C21: KR | D21: OPO | E21: 2026-06-18 | F21: minju | G21: MOARS | I21: Netherlands The | J21: KR-OVERSEAS | K21: RjAS01-CLC | L21: 어드벤스드 LC-세라마이드 베리어 크림 50ml | M21: 닥터 리쥬올 | N21: USD | O21: 300 | P21: 12.58 | Q21: 3,774.00 | R21: 0.00 | S21: 5,590,426.20 | T21: 15,000.00 | U21: 4,500,000.00 | V21: 1,090,426.20 | X21: 19.5 | Y21: IN00447658 | AA21: =LEFT(E21,7) -> 2026-06 | AB21: =IF(AND($AA21>="2025-01",$AA21<="2025-06"),"H1_2025",IF(AND($AA21>="2026-01",$AA21<="2026-06"),"H1_2026","")) -> H1_2026 | AC21: =IFERROR(VALUE(SUBSTITUTE(S21,",","")),0) -> 5590426.2 | AD21: =IFERROR(VALUE(SUBSTITUTE(O21,",","")),0) -> 300 | AE21: =IFERROR(VALUE(SUBSTITUTE(V21,",","")),0) -> 1090426.2 | AF21: =IF(ISNUMBER(SEARCH("FOC",W21)),"FOC",IF(ISNUMBER(SEARCH("샘플",W21)),"Sample","Paid")) -> Paid
A22: 20 | B22: 06312 | C22: KR | D22: OPO | E22: 2026-06-18 | F22: minju | G22: MOARS | I22: Netherlands The | J22: KR-OVERSEAS | K22: RjAS01-CREU | L22: [EU] 어드밴스드 PDRN 크림 20ml | M22: 닥터 리쥬올 | N22: USD | O22: 80 | P22: 0.01 | Q22: 0.80 | R22: 0.00 | S22: 1,185.04 | T22: 11,250.00 | U22: 900,000.00 | V22: -898,814.96 | W22: FOC (Free of charge, 판매장려금) | X22: -75,846.8 | Y22: IN00447658 | AA22: =LEFT(E22,7) -> 2026-06 | AB22: =IF(AND($AA22>="2025-01",$AA22<="2025-06"),"H1_2025",IF(AND($AA22>="2026-01",$AA22<="2026-06"),"H1_2026","")) -> H1_2026 | AC22: =IFERROR(VALUE(SUBSTITUTE(S22,",","")),0) -> 1185.04 | AD22: =IFERROR(VALUE(SUBSTITUTE(O22,",","")),0) -> 80 | AE22: =IFERROR(VALUE(SUBSTITUTE(V22,",","")),0) -> -898814.96 | AF22: =IF(ISNUMBER(SEARCH("FOC",W22)),"FOC",IF(ISNUMBER(SEARCH("샘플",W22)),"Sample","Paid")) -> FOC
A23: 21 | B23: 06312 | C23: KR | D23: OPO | E23: 2026-06-18 | F23: minju | G23: MOARS | I23: Netherlands The | J23: KR-OVERSEAS | K23: RjAS01-CREU | L23: [EU] 어드밴스드 PDRN 크림 20ml | M23: 닥터 리쥬올 | N23: USD | O23: 800 | P23: 13.30 | Q23: 10,640.00 | R23: 0.00 | S23: 15,761,032.00 | T23: 11,250.00 | U23: 9,000,000.00 | V23: 6,761,032.00 | X23: 42.9 | Y23: IN00447658 | AA23: =LEFT(E23,7) -> 2026-06 | AB23: =IF(AND($AA23>="2025-01",$AA23<="2025-06"),"H1_2025",IF(AND($AA23>="2026-01",$AA23<="2026-06"),"H1_2026","")) -> H1_2026 | AC23: =IFERROR(VALUE(SUBSTITUTE(S23,",","")),0) -> 15761032 | AD23: =IFERROR(VALUE(SUBSTITUTE(O23,",","")),0) -> 800 | AE23: =IFERROR(VALUE(SUBSTITUTE(V23,",","")),0) -> 6761032 | AF23: =IF(ISNUMBER(SEARCH("FOC",W23)),"FOC",IF(ISNUMBER(SEARCH("샘플",W23)),"Sample","Paid")) -> Paid
A24: 22 | B24: 06312 | C24: KR | D24: OPO | E24: 2026-06-18 | F24: minju | G24: MOARS | I24: Netherlands The | J24: KR-OVERSEAS | K24: RjAS01-CRMEU | L24: [EU] 어드밴스드 PDRN 크림 60ml | M24: 닥터 리쥬올 | N24: USD | O24: 400 | P24: 35.47 | Q24: 14,188.00 | R24: 0.00 | S24: 21,016,684.40 | T24: 32,000.00 | U24: 12,800,000.00 | V24: 8,216,684.40 | X24: 39.1 | Y24: IN00447658 | AA24: =LEFT(E24,7) -> 2026-06 | AB24: =IF(AND($AA24>="2025-01",$AA24<="2025-06"),"H1_2025",IF(AND($AA24>="2026-01",$AA24<="2026-06"),"H1_2026","")) -> H1_2026 | AC24: =IFERROR(VALUE(SUBSTITUTE(S24,",","")),0) -> 21016684 | AD24: =IFERROR(VALUE(SUBSTITUTE(O24,",","")),0) -> 400 | AE24: =IFERROR(VALUE(SUBSTITUTE(V24,",","")),0) -> 8216684.4 | AF24: =IF(ISNUMBER(SEARCH("FOC",W24)),"FOC",IF(ISNUMBER(SEARCH("샘플",W24)),"Sample","Paid")) -> Paid
A25: 23 | B25: 06312 | C25: KR | D25: OPO | E25: 2026-06-18 | F25: minju | G25: MOARS | I25: Netherlands The | J25: KR-OVERSEAS | K25: RjAS01-CRMEU | L25: [EU] 어드밴스드 PDRN 크림 60ml | M25: 닥터 리쥬올 | N25: USD | O25: 40 | P25: 0.01 | Q25: 0.40 | R25: 0.00 | S25: 592.52 | T25: 32,000.00 | U25: 1,280,000.00 | V25: -1,279,407.48 | W25: FOC (Free of charge, 판매장려금) | X25: -215,926.5 | Y25: IN00447658 | AA25: =LEFT(E25,7) -> 2026-06 | AB25: =IF(AND($AA25>="2025-01",$AA25<="2025-06"),"H1_2025",IF(AND($AA25>="2026-01",$AA25<="2026-06"),"H1_2026","")) -> H1_2026 | AC25: =IFERROR(VALUE(SUBSTITUTE(S25,",","")),0) -> 592.52 | AD25: =IFERROR(VALUE(SUBSTITUTE(O25,",","")),0) -> 40 | AE25: =IFERROR(VALUE(SUBSTITUTE(V25,",","")),0) -> -1279407.5 | AF25: =IF(ISNUMBER(SEARCH("FOC",W25)),"FOC",IF(ISNUMBER(SEARCH("샘플",W25)),"Sample","Paid")) -> FOC
A26: 24 | B26: 06312 | C26: KR | D26: OPO | E26: 2026-06-17 | F26: minju | G26: MOARS | I26: Netherlands The | J26: KR-OVERSEAS | K26: goodalS06-TPUS | L26: (글로벌) 청귤비타C 잡티 케어 패드 | M26: 구달 | N26: USD | O26: 24 | P26: 8.38 | Q26: 201.12 | R26: 0.00 | S26: 299,347.01 | T26: 9,454.55 | U26: 226,909.09 | V26: 72,437.92 | X26: 24.2 | Y26: IN00447659 | AA26: =LEFT(E26,7) -> 2026-06 | AB26: =IF(AND($AA26>="2025-01",$AA26<="2025-06"),"H1_2025",IF(AND($AA26>="2026-01",$AA26<="2026-06"),"H1_2026","")) -> H1_2026 | AC26: =IFERROR(VALUE(SUBSTITUTE(S26,",","")),0) -> 299347.01 | AD26: =IFERROR(VALUE(SUBSTITUTE(O26,",","")),0) -> 24 | AE26: =IFERROR(VALUE(SUBSTITUTE(V26,",","")),0) -> 72437.92 | AF26: =IF(ISNUMBER(SEARCH("FOC",W26)),"FOC",IF(ISNUMBER(SEARCH("샘플",W26)),"Sample","Paid")) -> Paid
A27: 25 | B27: 06312 | C27: KR | D27: OPO | E27: 2026-06-17 | F27: minju | G27: MOARS | I27: Netherlands The | J27: KR-OVERSEAS | K27: RjAS01-CLCEU | L27: [EU] 어드벤스드 LC-세라마이드 베리어 크림 50ml | M27: 닥터 리쥬올 | N27: USD | O27: 500 | P27: 12.58 | Q27: 6,290.00 | R27: 0.00 | S27: 9,362,036.00 | T27: 9,360.00 | U27: 4,680,000.00 | V27: 4,682,036.00 | X27: 50.0 | Y27: IN00447659 | AA27: =LEFT(E27,7) -> 2026-06 | AB27: =IF(AND($AA27>="2025-01",$AA27<="2025-06"),"H1_2025",IF(AND($AA27>="2026-01",$AA27<="2026-06"),"H1_2026","")) -> H1_2026 | AC27: =IFERROR(VALUE(SUBSTITUTE(S27,",","")),0) -> 9362036 | AD27: =IFERROR(VALUE(SUBSTITUTE(O27,",","")),0) -> 500 | AE27: =IFERROR(VALUE(SUBSTITUTE(V27,",","")),0) -> 4682036 | AF27: =IF(ISNUMBER(SEARCH("FOC",W27)),"FOC",IF(ISNUMBER(SEARCH("샘플",W27)),"Sample","Paid")) -> Paid
A28: 26 | B28: 06312 | C28: KR | D28: OPO | E28: 2026-06-17 | F28: minju | G28: MOARS | I28: Netherlands The | J28: KR-OVERSEAS | K28: RjAS01-CLCEU | L28: [EU] 어드벤스드 LC-세라마이드 베리어 크림 50ml | M28: 닥터 리쥬올 | N28: USD | O28: 50 | P28: 0.01 | Q28: 0.50 | R28: 0.00 | S28: 744.20 | T28: 9,360.00 | U28: 468,000.00 | V28: -467,255.80 | W28: FOC (Free of charge, 판매장려금) | X28: -62,786.3 | Y28: IN00447659 | AA28: =LEFT(E28,7) -> 2026-06 | AB28: =IF(AND($AA28>="2025-01",$AA28<="2025-06"),"H1_2025",IF(AND($AA28>="2026-01",$AA28<="2026-06"),"H1_2026","")) -> H1_2026 | AC28: =IFERROR(VALUE(SUBSTITUTE(S28,",","")),0) -> 744.2 | AD28: =IFERROR(VALUE(SUBSTITUTE(O28,",","")),0) -> 50 | AE28: =IFERROR(VALUE(SUBSTITUTE(V28,",","")),0) -> -467255.8 | AF28: =IF(ISNUMBER(SEARCH("FOC",W28)),"FOC",IF(ISNUMBER(SEARCH("샘플",W28)),"Sample","Paid")) -> FOC
A29: 27 | B29: 06312 | C29: KR | D29: OPO | E29: 2026-06-17 | F29: minju | G29: MOARS | I29: Netherlands The | J29: KR-OVERSEAS | K29: RjAS01-CREU | L29: [EU] 어드밴스드 PDRN 크림 20ml | M29: 닥터 리쥬올 | N29: USD | O29: 140 | P29: 0.01 | Q29: 1.40 | R29: 0.00 | S29: 2,083.76 | T29: 11,250.00 | U29: 1,575,000.00 | V29: -1,572,916.24 | W29: FOC (Free of charge, 판매장려금) | X29: -75,484.5 | Y29: IN00447659 | AA29: =LEFT(E29,7) -> 2026-06 | AB29: =IF(AND($AA29>="2025-01",$AA29<="2025-06"),"H1_2025",IF(AND($AA29>="2026-01",$AA29<="2026-06"),"H1_2026","")) -> H1_2026 | AC29: =IFERROR(VALUE(SUBSTITUTE(S29,",","")),0) -> 2083.76 | AD29: =IFERROR(VALUE(SUBSTITUTE(O29,",","")),0) -> 140 | AE29: =IFERROR(VALUE(SUBSTITUTE(V29,",","")),0) -> -1572916.2 | AF29: =IF(ISNUMBER(SEARCH("FOC",W29)),"FOC",IF(ISNUMBER(SEARCH("샘플",W29)),"Sample","Paid")) -> FOC
A30: 28 | B30: 06312 | C30: KR | D30: OPO | E30: 2026-06-17 | F30: minju | G30: MOARS | I30: Netherlands The | J30: KR-OVERSEAS | K30: RjAS01-CREU | L30: [EU] 어드밴스드 PDRN 크림 20ml | M30: 닥터 리쥬올 | N30: USD | O30: 1,400 | P30: 13.30 | Q30: 18,620.00 | R30: 0.00 | S30: 27,714,008.00 | T30: 11,250.00 | U30: 15,750,000.00 | V30: 11,964,008.00 | X30: 43.2 | Y30: IN00447659 | AA30: =LEFT(E30,7) -> 2026-06 | AB30: =IF(AND($AA30>="2025-01",$AA30<="2025-06"),"H1_2025",IF(AND($AA30>="2026-01",$AA30<="2026-06"),"H1_2026","")) -> H1_2026 | AC30: =IFERROR(VALUE(SUBSTITUTE(S30,",","")),0) -> 27714008 | AD30: =IFERROR(VALUE(SUBSTITUTE(O30,",","")),0) -> 1400 | AE30: =IFERROR(VALUE(SUBSTITUTE(V30,",","")),0) -> 11964008 | AF30: =IF(ISNUMBER(SEARCH("FOC",W30)),"FOC",IF(ISNUMBER(SEARCH("샘플",W30)),"Sample","Paid")) -> Paid
A31: 29 | B31: 06312 | C31: KR | D31: OPO | E31: 2026-06-17 | F31: minju | G31: MOARS | I31: Netherlands The | J31: KR-OVERSEAS | K31: RjAS01-CRMEU | L31: [EU] 어드밴스드 PDRN 크림 60ml | M31: 닥터 리쥬올 | N31: USD | O31: 80 | P31: 0.01 | Q31: 0.80 | R31: 0.00 | S31: 1,190.72 | T31: 32,000.00 | U31: 2,560,000.00 | V31: -2,558,809.28 | W31: FOC (Free of charge, 판매장려금) | X31: -214,896.0 | Y31: IN00447659 | AA31: =LEFT(E31,7) -> 2026-06 | AB31: =IF(AND($AA31>="2025-01",$AA31<="2025-06"),"H1_2025",IF(AND($AA31>="2026-01",$AA31<="2026-06"),"H1_2026","")) -> H1_2026 | AC31: =IFERROR(VALUE(SUBSTITUTE(S31,",","")),0) -> 1190.72 | AD31: =IFERROR(VALUE(SUBSTITUTE(O31,",","")),0) -> 80 | AE31: =IFERROR(VALUE(SUBSTITUTE(V31,",","")),0) -> -2558809.3 | AF31: =IF(ISNUMBER(SEARCH("FOC",W31)),"FOC",IF(ISNUMBER(SEARCH("샘플",W31)),"Sample","Paid")) -> FOC
A32: 30 | B32: 06312 | C32: KR | D32: OPO | E32: 2026-06-17 | F32: minju | G32: MOARS | I32: Netherlands The | J32: KR-OVERSEAS | K32: RjAS01-CRMEU | L32: [EU] 어드밴스드 PDRN 크림 60ml | M32: 닥터 리쥬올 | N32: USD | O32: 800 | P32: 35.47 | Q32: 28,376.00 | R32: 0.00 | S32: 42,234,838.40 | T32: 32,000.00 | U32: 25,600,000.00 | V32: 16,634,838.40 | X32: 39.4 | Y32: IN00447659 | AA32: =LEFT(E32,7) -> 2026-06 | AB32: =IF(AND($AA32>="2025-01",$AA32<="2025-06"),"H1_2025",IF(AND($AA32>="2026-01",$AA32<="2026-06"),"H1_2026","")) -> H1_2026 | AC32: =IFERROR(VALUE(SUBSTITUTE(S32,",","")),0) -> 42234838 | AD32: =IFERROR(VALUE(SUBSTITUTE(O32,",","")),0) -> 800 | AE32: =IFERROR(VALUE(SUBSTITUTE(V32,",","")),0) -> 16634838 | AF32: =IF(ISNUMBER(SEARCH("FOC",W32)),"FOC",IF(ISNUMBER(SEARCH("샘플",W32)),"Sample","Paid")) -> Paid
A33: 31 | B33: 06312 | C33: KR | D33: OPO | E33: 2026-06-17 | F33: minju | G33: MOARS | I33: Netherlands The | J33: KR-OVERSEAS | K33: RjAS01-SM | L33: 어드밴스드 레티노-멜라 세럼 30ml | M33: 닥터 리쥬올 | N33: USD | O33: 40 | P33: 0.01 | Q33: 0.40 | R33: 0.00 | S33: 595.36 | T33: 18,500.00 | U33: 740,000.00 | V33: -739,404.64 | W33: FOC (Free of charge, 판매장려금) | X33: -124,194.5 | Y33: IN00447659 | AA33: =LEFT(E33,7) -> 2026-06 | AB33: =IF(AND($AA33>="2025-01",$AA33<="2025-06"),"H1_2025",IF(AND($AA33>="2026-01",$AA33<="2026-06"),"H1_2026","")) -> H1_2026 | AC33: =IFERROR(VALUE(SUBSTITUTE(S33,",","")),0) -> 595.36 | AD33: =IFERROR(VALUE(SUBSTITUTE(O33,",","")),0) -> 40 | AE33: =IFERROR(VALUE(SUBSTITUTE(V33,",","")),0) -> -739404.64 | AF33: =IF(ISNUMBER(SEARCH("FOC",W33)),"FOC",IF(ISNUMBER(SEARCH("샘플",W33)),"Sample","Paid")) -> FOC
A34: 32 | B34: 06312 | C34: KR | D34: OPO | E34: 2026-06-17 | F34: minju | G34: MOARS | I34: Netherlands The | J34: KR-OVERSEAS | K34: RjAS01-SM | L34: 어드밴스드 레티노-멜라 세럼 30ml | M34: 닥터 리쥬올 | N34: USD | O34: 400 | P34: 15.48 | Q34: 6,192.00 | R34: 0.00 | S34: 9,216,172.80 | T34: 18,500.00 | U34: 7,400,000.00 | V34: 1,816,172.80 | X34: 19.7 | Y34: IN00447659 | AA34: =LEFT(E34,7) -> 2026-06 | AB34: =IF(AND($AA34>="2025-01",$AA34<="2025-06"),"H1_2025",IF(AND($AA34>="2026-01",$AA34<="2026-06"),"H1_2026","")) -> H1_2026 | AC34: =IFERROR(VALUE(SUBSTITUTE(S34,",","")),0) -> 9216172.8 | AD34: =IFERROR(VALUE(SUBSTITUTE(O34,",","")),0) -> 400 | AE34: =IFERROR(VALUE(SUBSTITUTE(V34,",","")),0) -> 1816172.8 | AF34: =IF(ISNUMBER(SEARCH("FOC",W34)),"FOC",IF(ISNUMBER(SEARCH("샘플",W34)),"Sample","Paid")) -> Paid
A35: 33 | B35: 06312 | C35: KR | D35: OPO | E35: 2026-06-16 | F35: minju | G35: MOARS | I35: Netherlands The | J35: KR-OVERSEAS | K35: ALSC01-Fbr | L35: (리뉴얼) 프레시 블루 히솝 라이스 모찌 클렌저 120g | M35: 아렌시아 | N35: USD | O35: 2 | P35: 6.24 | Q35: 12.48 | R35: 0.00 | S35: 18,389.28 | T35: 6,600.00 | U35: 13,200.00 | V35: 5,189.28 | X35: 28.2 | Y35: IN00444093 | AA35: =LEFT(E35,7) -> 2026-06 | AB35: =IF(AND($AA35>="2025-01",$AA35<="2025-06"),"H1_2025",IF(AND($AA35>="2026-01",$AA35<="2026-06"),"H1_2026","")) -> H1_2026 | AC35: =IFERROR(VALUE(SUBSTITUTE(S35,",","")),0) -> 18389.28 | AD35: =IFERROR(VALUE(SUBSTITUTE(O35,",","")),0) -> 2 | AE35: =IFERROR(VALUE(SUBSTITUTE(V35,",","")),0) -> 5189.28 | AF35: =IF(ISNUMBER(SEARCH("FOC",W35)),"FOC",IF(ISNUMBER(SEARCH("샘플",W35)),"Sample","Paid")) -> Paid
A36: 34 | B36: 06312 | C36: KR | D36: OPO | E36: 2026-06-16 | F36: minju | G36: MOARS | I36: Netherlands The | J36: KR-OVERSEAS | K36: ALSC01-Fgr | L36: (리뉴얼) 프레시 그린 라이스 모찌 클렌저 120G | M36: 아렌시아 | N36: USD | O36: 580 | P36: 6.24 | Q36: 3,619.20 | R36: 0.00 | S36: 5,332,891.20 | T36: 6,600.00 | U36: 3,828,000.00 | V36: 1,504,891.20 | X36: 28.2 | Y36: IN00444093 | AA36: =LEFT(E36,7) -> 2026-06 | AB36: =IF(AND($AA36>="2025-01",$AA36<="2025-06"),"H1_2025",IF(AND($AA36>="2026-01",$AA36<="2026-06"),"H1_2026","")) -> H1_2026 | AC36: =IFERROR(VALUE(SUBSTITUTE(S36,",","")),0) -> 5332891.2 | AD36: =IFERROR(VALUE(SUBSTITUTE(O36,",","")),0) -> 580 | AE36: =IFERROR(VALUE(SUBSTITUTE(V36,",","")),0) -> 1504891.2 | AF36: =IF(ISNUMBER(SEARCH("FOC",W36)),"FOC",IF(ISNUMBER(SEARCH("샘플",W36)),"Sample","Paid")) -> Paid
A37: 35 | B37: 06312 | C37: KR | D37: OPO | E37: 2026-06-16 | F37: minju | G37: MOARS | I37: Netherlands The | J37: KR-OVERSEAS | K37: ALSS11-SR | L37: 레틴알 부스터 샷 30ml | M37: 아렌시아 | N37: USD | O37: 610 | P37: 7.78 | Q37: 4,745.80 | R37: 0.00 | S37: 6,992,936.30 | T37: 7,000.00 | U37: 4,270,000.00 | V37: 2,722,936.30 | X37: 38.9 | Y37: IN00444093 | AA37: =LEFT(E37,7) -> 2026-06 | AB37: =IF(AND($AA37>="2025-01",$AA37<="2025-06"),"H1_2025",IF(AND($AA37>="2026-01",$AA37<="2026-06"),"H1_2026","")) -> H1_2026 | AC37: =IFERROR(VALUE(SUBSTITUTE(S37,",","")),0) -> 6992936.3 | AD37: =IFERROR(VALUE(SUBSTITUTE(O37,",","")),0) -> 610 | AE37: =IFERROR(VALUE(SUBSTITUTE(V37,",","")),0) -> 2722936.3 | AF37: =IF(ISNUMBER(SEARCH("FOC",W37)),"FOC",IF(ISNUMBER(SEARCH("샘플",W37)),"Sample","Paid")) -> Paid
A38: 36 | B38: 06312 | C38: KR | D38: OPO | E38: 2026-06-16 | F38: minju | G38: MOARS | I38: Netherlands The | J38: KR-OVERSEAS | K38: ALSS11-SV | L38: 비타민 C 부스터 샷 30ml | M38: 아렌시아 | N38: USD | O38: 2,600 | P38: 7.78 | Q38: 20,228.00 | R38: 0.00 | S38: 29,805,958.00 | T38: 8,000.00 | U38: 20,800,000.00 | V38: 9,005,958.00 | X38: 30.2 | Y38: IN00444093 | AA38: =LEFT(E38,7) -> 2026-06 | AB38: =IF(AND($AA38>="2025-01",$AA38<="2025-06"),"H1_2025",IF(AND($AA38>="2026-01",$AA38<="2026-06"),"H1_2026","")) -> H1_2026 | AC38: =IFERROR(VALUE(SUBSTITUTE(S38,",","")),0) -> 29805958 | AD38: =IFERROR(VALUE(SUBSTITUTE(O38,",","")),0) -> 2600 | AE38: =IFERROR(VALUE(SUBSTITUTE(V38,",","")),0) -> 9005958 | AF38: =IF(ISNUMBER(SEARCH("FOC",W38)),"FOC",IF(ISNUMBER(SEARCH("샘플",W38)),"Sample","Paid")) -> Paid
A39: 37 | B39: 06312 | C39: KR | D39: OPO | E39: 2026-06-16 | F39: minju | G39: MOARS | I39: Netherlands The | J39: KR-OVERSEAS | K39: ANC01-FQRRR | L39: [리뉴얼] 어성초 쿼세티놀 모공 딥 클렌징폼 150ml | M39: 아누아 | N39: USD | O39: 9,770 | P39: 5.99 | Q39: 58,522.30 | R39: 0.00 | S39: 86,232,609.05 | T39: 7,760.00 | U39: 75,815,200.00 | V39: 10,417,409.05 | X39: 12.1 | Y39: IN00444093 | AA39: =LEFT(E39,7) -> 2026-06 | AB39: =IF(AND($AA39>="2025-01",$AA39<="2025-06"),"H1_2025",IF(AND($AA39>="2026-01",$AA39<="2026-06"),"H1_2026","")) -> H1_2026 | AC39: =IFERROR(VALUE(SUBSTITUTE(S39,",","")),0) -> 86232609 | AD39: =IFERROR(VALUE(SUBSTITUTE(O39,",","")),0) -> 9770 | AE39: =IFERROR(VALUE(SUBSTITUTE(V39,",","")),0) -> 10417409 | AF39: =IF(ISNUMBER(SEARCH("FOC",W39)),"FOC",IF(ISNUMBER(SEARCH("샘플",W39)),"Sample","Paid")) -> Paid
A40: 38 | B40: 06312 | C40: KR | D40: OPO | E40: 2026-06-16 | F40: minju | G40: MOARS | I40: Netherlands The | J40: KR-OVERSEAS | K40: ANC01-FSR | L40: [리뉴얼] 어성초 석시닉 모이스처 클렌징폼 150ml | M40: 아누아 | N40: USD | O40: 290 | P40: 6.01 | Q40: 1,742.90 | R40: 0.00 | S40: 2,568,163.15 | T40: 7,760.00 | U40: 2,250,400.00 | V40: 317,763.15 | X40: 12.4 | Y40: IN00444093 | AA40: =LEFT(E40,7) -> 2026-06 | AB40: =IF(AND($AA40>="2025-01",$AA40<="2025-06"),"H1_2025",IF(AND($AA40>="2026-01",$AA40<="2026-06"),"H1_2026","")) -> H1_2026 | AC40: =IFERROR(VALUE(SUBSTITUTE(S40,",","")),0) -> 2568163.1 | AD40: =IFERROR(VALUE(SUBSTITUTE(O40,",","")),0) -> 290 | AE40: =IFERROR(VALUE(SUBSTITUTE(V40,",","")),0) -> 317763.15 | AF40: =IF(ISNUMBER(SEARCH("FOC",W40)),"FOC",IF(ISNUMBER(SEARCH("샘플",W40)),"Sample","Paid")) -> Paid
A41: 39 | B41: 06312 | C41: KR | D41: OPO | E41: 2026-06-16 | F41: minju | G41: MOARS | I41: Netherlands The | J41: KR-OVERSEAS | K41: ANC01-OCR | L41: [리뉴얼] 어성초 포어 컨트롤 클렌징 오일 200ml | M41: 아누아 | N41: USD | O41: 10,570 | P41: 8.51 | Q41: 89,950.70 | R41: 0.00 | S41: 132,542,356.45 | T41: 5,572.50 | U41: 58,901,280.00 | V41: 73,641,076.45 | X41: 55.6 | Y41: IN00444093 | AA41: =LEFT(E41,7) -> 2026-06 | AB41: =IF(AND($AA41>="2025-01",$AA41<="2025-06"),"H1_2025",IF(AND($AA41>="2026-01",$AA41<="2026-06"),"H1_2026","")) -> H1_2026 | AC41: =IFERROR(VALUE(SUBSTITUTE(S41,",","")),0) -> 1.3254236e+08 | AD41: =IFERROR(VALUE(SUBSTITUTE(O41,",","")),0) -> 10570 | AE41: =IFERROR(VALUE(SUBSTITUTE(V41,",","")),0) -> 73641076 | AF41: =IF(ISNUMBER(SEARCH("FOC",W41)),"FOC",IF(ISNUMBER(SEARCH("샘플",W41)),"Sample","Paid")) -> Paid
A42: 40 | B42: 06312 | C42: KR | D42: OPO | E42: 2026-06-16 | F42: minju | G42: MOARS | I42: Netherlands The | J42: KR-OVERSEAS | K42: ANC06-F | L42: [리뉴얼] 복숭아 나이아신 클렌징폼 150ml | M42: 아누아 | N42: USD | O42: 300 | P42: 5.99 | Q42: 1,797.00 | R42: 0.00 | S42: 2,647,879.50 | T42: 7,760.00 | U42: 2,328,000.00 | V42: 319,879.50 | X42: 12.1 | Y42: IN00444093 | AA42: =LEFT(E42,7) -> 2026-06 | AB42: =IF(AND($AA42>="2025-01",$AA42<="2025-06"),"H1_2025",IF(AND($AA42>="2026-01",$AA42<="2026-06"),"H1_2026","")) -> H1_2026 | AC42: =IFERROR(VALUE(SUBSTITUTE(S42,",","")),0) -> 2647879.5 | AD42: =IFERROR(VALUE(SUBSTITUTE(O42,",","")),0) -> 300 | AE42: =IFERROR(VALUE(SUBSTITUTE(V42,",","")),0) -> 319879.5 | AF42: =IF(ISNUMBER(SEARCH("FOC",W42)),"FOC",IF(ISNUMBER(SEARCH("샘플",W42)),"Sample","Paid")) -> Paid
A43: 41 | B43: 06312 | C43: KR | D43: OPO | E43: 2026-06-16 | F43: minju | G43: MOARS | I43: Netherlands The | J43: KR-OVERSEAS | K43: ANC11-FP | L43: 라이스 효소 브라이트닝 클렌징 파우더 40g | M43: 아누아 | N43: USD | O43: 670 | P43: 7.63 | Q43: 5,112.10 | R43: 0.00 | S43: 7,532,679.35 | T43: 9,970.00 | U43: 6,679,900.00 | V43: 852,779.35 | X43: 11.3 | Y43: IN00444093 | AA43: =LEFT(E43,7) -> 2026-06 | AB43: =IF(AND($AA43>="2025-01",$AA43<="2025-06"),"H1_2025",IF(AND($AA43>="2026-01",$AA43<="2026-06"),"H1_2026","")) -> H1_2026 | AC43: =IFERROR(VALUE(SUBSTITUTE(S43,",","")),0) -> 7532679.3 | AD43: =IFERROR(VALUE(SUBSTITUTE(O43,",","")),0) -> 670 | AE43: =IFERROR(VALUE(SUBSTITUTE(V43,",","")),0) -> 852779.35 | AF43: =IF(ISNUMBER(SEARCH("FOC",W43)),"FOC",IF(ISNUMBER(SEARCH("샘플",W43)),"Sample","Paid")) -> Paid
A44: 42 | B44: 06312 | C44: KR | D44: OPO | E44: 2026-06-16 | F44: minju | G44: MOARS | I44: Netherlands The | J44: KR-OVERSEAS | K44: ANC12-F | L44: 8 히알루론산 하이드레이팅 젠틀 포밍 클렌저 150ml | M44: 아누아 | N44: USD | O44: 710 | P44: 5.99 | Q44: 4,252.90 | R44: 0.00 | S44: 6,266,648.15 | T44: 7,760.00 | U44: 5,509,600.00 | V44: 757,048.15 | X44: 12.1 | Y44: IN00444093 | AA44: =LEFT(E44,7) -> 2026-06 | AB44: =IF(AND($AA44>="2025-01",$AA44<="2025-06"),"H1_2025",IF(AND($AA44>="2026-01",$AA44<="2026-06"),"H1_2026","")) -> H1_2026 | AC44: =IFERROR(VALUE(SUBSTITUTE(S44,",","")),0) -> 6266648.2 | AD44: =IFERROR(VALUE(SUBSTITUTE(O44,",","")),0) -> 710 | AE44: =IFERROR(VALUE(SUBSTITUTE(V44,",","")),0) -> 757048.15 | AF44: =IF(ISNUMBER(SEARCH("FOC",W44)),"FOC",IF(ISNUMBER(SEARCH("샘플",W44)),"Sample","Paid")) -> Paid
A45: 43 | B45: 06312 | C45: KR | D45: OPO | E45: 2026-06-16 | F45: minju | G45: MOARS | I45: Netherlands The | J45: KR-OVERSEAS | K45: ANC12-FMG | L45: 8 히알루론산 모이스처라이징 젠틀 젤 클렌저 150ml | M45: 아누아 | N45: USD | O45: 320 | P45: 5.99 | Q45: 1,916.80 | R45: 0.00 | S45: 2,824,404.80 | T45: 7,760.00 | U45: 2,483,200.00 | V45: 341,204.80 | X45: 12.1 | Y45: IN00444093 | AA45: =LEFT(E45,7) -> 2026-06 | AB45: =IF(AND($AA45>="2025-01",$AA45<="2025-06"),"H1_2025",IF(AND($AA45>="2026-01",$AA45<="2026-06"),"H1_2026","")) -> H1_2026 | AC45: =IFERROR(VALUE(SUBSTITUTE(S45,",","")),0) -> 2824404.8 | AD45: =IFERROR(VALUE(SUBSTITUTE(O45,",","")),0) -> 320 | AE45: =IFERROR(VALUE(SUBSTITUTE(V45,",","")),0) -> 341204.8 | AF45: =IF(ISNUMBER(SEARCH("FOC",W45)),"FOC",IF(ISNUMBER(SEARCH("샘플",W45)),"Sample","Paid")) -> Paid
... A217: 215 | B217: 06312 | C217: KR | D217: OPO | E217: 2026-06-08 | F217: minju | G217: MOARS | I217: Netherlands The | J217: KR-OVERSEAS | K217: JSMS01-TRR | L217: [한국콜마/리뉴얼]청매실AHABHA토너 150ml | M217: 조선미녀 | N217: USD | O217: 4,850 | P217: 5.60 | Q217: 27,160.00 | R217: 0.00 | S217: 39,001,760.00 | T217: 7,560.00 | U217: 36,666,000.00 | V217: 2,335,760.00 | X217: 6.0 | Y217: IN00441298 | AA217: =LEFT(E217,7) -> 2026-06 | AB217: =IF(AND($AA217>="2025-01",$AA217<="2025-06"),"H1_2025",IF(AND($AA217>="2026-01",$AA217<="2026-06"),"H1_2026","")) -> H1_2026 | AC217: =IFERROR(VALUE(SUBSTITUTE(S217,",","")),0) -> 39001760 | AD217: =IFERROR(VALUE(SUBSTITUTE(O217,",","")),0) -> 4850 | AE217: =IFERROR(VALUE(SUBSTITUTE(V217,",","")),0) -> 2335760 | AF217: =IF(ISNUMBER(SEARCH("FOC",W217)),"FOC",IF(ISNUMBER(SEARCH("샘플",W217)),"Sample","Paid")) -> Paid
A218: 216 | B218: 06312 | C218: KR | D218: OPO | E218: 2026-06-08 | F218: minju | G218: MOARS | I218: Netherlands The | J218: KR-OVERSEAS | K218: KLVP07-LipPKCR | L218: [R] 너리싱 케어 립 슬리핑 팩 코코넛 | M218: 클라뷰 | N218: USD | O218: 2,550 | P218: 0.00 | Q218: 0.00 | R218: 0.00 | S218: 0.00 | T218: 361.95 | U218: 922,981.82 | V218: -922,981.82 | W218: FOC (Free of charge, 판매장려금) | X218: 0.0 | Y218: IN00441298 | AA218: =LEFT(E218,7) -> 2026-06 | AB218: =IF(AND($AA218>="2025-01",$AA218<="2025-06"),"H1_2025",IF(AND($AA218>="2026-01",$AA218<="2026-06"),"H1_2026","")) -> H1_2026 | AC218: =IFERROR(VALUE(SUBSTITUTE(S218,",","")),0) -> 0 | AD218: =IFERROR(VALUE(SUBSTITUTE(O218,",","")),0) -> 2550 | AE218: =IFERROR(VALUE(SUBSTITUTE(V218,",","")),0) -> -922981.82 | AF218: =IF(ISNUMBER(SEARCH("FOC",W218)),"FOC",IF(ISNUMBER(SEARCH("샘플",W218)),"Sample","Paid")) -> FOC
A219: 217 | B219: 06312 | C219: KR | D219: OPO | E219: 2026-06-08 | F219: minju | G219: MOARS | I219: Netherlands The | J219: KR-OVERSEAS | K219: KLVP07-LipPKCR | L219: [R] 너리싱 케어 립 슬리핑 팩 코코넛 | M219: 클라뷰 | N219: USD | O219: 2,300 | P219: 3.03 | Q219: 6,969.00 | R219: 0.00 | S219: 10,007,484.00 | T219: 3,296.36 | U219: 7,581,636.28 | V219: 2,425,847.72 | X219: 24.2 | Y219: IN00441298 | AA219: =LEFT(E219,7) -> 2026-06 | AB219: =IF(AND($AA219>="2025-01",$AA219<="2025-06"),"H1_2025",IF(AND($AA219>="2026-01",$AA219<="2026-06"),"H1_2026","")) -> H1_2026 | AC219: =IFERROR(VALUE(SUBSTITUTE(S219,",","")),0) -> 10007484 | AD219: =IFERROR(VALUE(SUBSTITUTE(O219,",","")),0) -> 2300 | AE219: =IFERROR(VALUE(SUBSTITUTE(V219,",","")),0) -> 2425847.7 | AF219: =IF(ISNUMBER(SEARCH("FOC",W219)),"FOC",IF(ISNUMBER(SEARCH("샘플",W219)),"Sample","Paid")) -> Paid
A220: 218 | B220: 06312 | C220: KR | D220: OPO | E220: 2026-06-08 | F220: minju | G220: MOARS | I220: Netherlands The | J220: KR-OVERSEAS | K220: MECUP10-PKR | L220: 콜라겐 나이트 랩핑 마스크 75ml | M220: 메디큐브 | N220: USD | O220: 4,850 | P220: 8.35 | Q220: 40,497.50 | R220: 0.00 | S220: 58,154,410.00 | T220: 10,260.00 | U220: 49,761,000.00 | V220: 8,393,410.00 | X220: 14.4 | Y220: IN00441298 | AA220: =LEFT(E220,7) -> 2026-06 | AB220: =IF(AND($AA220>="2025-01",$AA220<="2025-06"),"H1_2025",IF(AND($AA220>="2026-01",$AA220<="2026-06"),"H1_2026","")) -> H1_2026 | AC220: =IFERROR(VALUE(SUBSTITUTE(S220,",","")),0) -> 58154410 | AD220: =IFERROR(VALUE(SUBSTITUTE(O220,",","")),0) -> 4850 | AE220: =IFERROR(VALUE(SUBSTITUTE(V220,",","")),0) -> 8393410 | AF220: =IF(ISNUMBER(SEARCH("FOC",W220)),"FOC",IF(ISNUMBER(SEARCH("샘플",W220)),"Sample","Paid")) -> Paid
A221: 219 | B221: 06312 | C221: KR | D221: OPO | E221: 2026-06-08 | F221: minju | G221: MOARS | I221: Netherlands The | J221: KR-OVERSEAS | K221: PRS07-TPD | L221: (통합) 오트 피디알엔 젠틀 리파이닝 토너 200ml | M221: 퓨리토 서울 | N221: USD | O221: 4,850 | P221: 5.68 | Q221: 27,548.00 | R221: 0.00 | S221: 39,558,928.00 | T221: 6,787.70 | U221: 32,920,362.46 | V221: 6,638,565.54 | X221: 16.8 | Y221: IN00441298 | AA221: =LEFT(E221,7) -> 2026-06 | AB221: =IF(AND($AA221>="2025-01",$AA221<="2025-06"),"H1_2025",IF(AND($AA221>="2026-01",$AA221<="2026-06"),"H1_2026","")) -> H1_2026 | AC221: =IFERROR(VALUE(SUBSTITUTE(S221,",","")),0) -> 39558928 | AD221: =IFERROR(VALUE(SUBSTITUTE(O221,",","")),0) -> 4850 | AE221: =IFERROR(VALUE(SUBSTITUTE(V221,",","")),0) -> 6638565.5 | AF221: =IF(ISNUMBER(SEARCH("FOC",W221)),"FOC",IF(ISNUMBER(SEARCH("샘플",W221)),"Sample","Paid")) -> Paid
A222: 220 | B222: 06312 | C222: KR | D222: OPO | E222: 2026-06-08 | F222: minju | G222: MOARS | I222: Netherlands The | J222: KR-OVERSEAS | K222: PYS01-IBTR | L222: *리뉴얼 블랙티 타임 리버스 아이크림 25ml | M222: 편강율 | N222: USD | O222: 1,100 | P222: 9.75 | Q222: 10,725.00 | R222: 0.00 | S222: 15,401,100.00 | T222: 12,000.00 | U222: 13,200,000.00 | V222: 2,201,100.00 | X222: 14.3 | Y222: IN00441298 | AA222: =LEFT(E222,7) -> 2026-06 | AB222: =IF(AND($AA222>="2025-01",$AA222<="2025-06"),"H1_2025",IF(AND($AA222>="2026-01",$AA222<="2026-06"),"H1_2026","")) -> H1_2026 | AC222: =IFERROR(VALUE(SUBSTITUTE(S222,",","")),0) -> 15401100 | AD222: =IFERROR(VALUE(SUBSTITUTE(O222,",","")),0) -> 1100 | AE222: =IFERROR(VALUE(SUBSTITUTE(V222,",","")),0) -> 2201100 | AF222: =IF(ISNUMBER(SEARCH("FOC",W222)),"FOC",IF(ISNUMBER(SEARCH("샘플",W222)),"Sample","Paid")) -> Paid
A223: 221 | B223: 06312 | C223: KR | D223: OPO | E223: 2026-06-08 | F223: minju | G223: MOARS | I223: Netherlands The | J223: KR-OVERSEAS | K223: PYS01-IBTR | L223: *리뉴얼 블랙티 타임 리버스 아이크림 25ml | M223: 편강율 | N223: USD | O223: 3,750 | P223: 0.00 | Q223: 0.00 | R223: 0.00 | S223: 0.00 | T223: 158.24 | U223: 593,400.00 | V223: -593,400.00 | W223: FOC (Free of charge, 판매장려금) | X223: 0.0 | Y223: IN00441298 | AA223: =LEFT(E223,7) -> 2026-06 | AB223: =IF(AND($AA223>="2025-01",$AA223<="2025-06"),"H1_2025",IF(AND($AA223>="2026-01",$AA223<="2026-06"),"H1_2026","")) -> H1_2026 | AC223: =IFERROR(VALUE(SUBSTITUTE(S223,",","")),0) -> 0 | AD223: =IFERROR(VALUE(SUBSTITUTE(O223,",","")),0) -> 3750 | AE223: =IFERROR(VALUE(SUBSTITUTE(V223,",","")),0) -> -593400 | AF223: =IF(ISNUMBER(SEARCH("FOC",W223)),"FOC",IF(ISNUMBER(SEARCH("샘플",W223)),"Sample","Paid")) -> FOC
A224: 222 | B224: 06312 | C224: KR | D224: OPO | E224: 2026-06-08 | F224: minju | G224: MOARS | I224: Netherlands The | J224: KR-OVERSEAS | K224: ES84-01BR | L224: (23AD) 마이래쉬세럼 18g | M224: 에뛰드 | N224: USD | O224: 200 | P224: 3.65 | Q224: 730.00 | R224: 0.00 | S224: 1,048,280.00 | T224: 4,700.00 | U224: 940,000.00 | V224: 108,280.00 | X224: 10.3 | Y224: IN00441297 | AA224: =LEFT(E224,7) -> 2026-06 | AB224: =IF(AND($AA224>="2025-01",$AA224<="2025-06"),"H1_2025",IF(AND($AA224>="2026-01",$AA224<="2026-06"),"H1_2026","")) -> H1_2026 | AC224: =IFERROR(VALUE(SUBSTITUTE(S224,",","")),0) -> 1048280 | AD224: =IFERROR(VALUE(SUBSTITUTE(O224,",","")),0) -> 200 | AE224: =IFERROR(VALUE(SUBSTITUTE(V224,",","")),0) -> 108280 | AF224: =IF(ISNUMBER(SEARCH("FOC",W224)),"FOC",IF(ISNUMBER(SEARCH("샘플",W224)),"Sample","Paid")) -> Paid
A225: 223 | B225: 06312 | C225: KR | D225: OPO | E225: 2026-06-08 | F225: minju | G225: MOARS | I225: Netherlands The | J225: KR-OVERSEAS | K225: JSMS01-TRR | L225: [한국콜마/리뉴얼]청매실AHABHA토너 150ml | M225: 조선미녀 | N225: USD | O225: 200 | P225: 5.60 | Q225: 1,120.00 | R225: 0.00 | S225: 1,608,320.00 | T225: 7,560.00 | U225: 1,512,000.00 | V225: 96,320.00 | X225: 6.0 | Y225: IN00441297 | AA225: =LEFT(E225,7) -> 2026-06 | AB225: =IF(AND($AA225>="2025-01",$AA225<="2025-06"),"H1_2025",IF(AND($AA225>="2026-01",$AA225<="2026-06"),"H1_2026","")) -> H1_2026 | AC225: =IFERROR(VALUE(SUBSTITUTE(S225,",","")),0) -> 1608320 | AD225: =IFERROR(VALUE(SUBSTITUTE(O225,",","")),0) -> 200 | AE225: =IFERROR(VALUE(SUBSTITUTE(V225,",","")),0) -> 96320 | AF225: =IF(ISNUMBER(SEARCH("FOC",W225)),"FOC",IF(ISNUMBER(SEARCH("샘플",W225)),"Sample","Paid")) -> Paid
A226: 224 | B226: 06312 | C226: KR | D226: OPO | E226: 2026-06-08 | F226: minju | G226: MOARS | I226: Netherlands The | J226: KR-OVERSEAS | K226: KLVP07-LipPKCR | L226: [R] 너리싱 케어 립 슬리핑 팩 코코넛 | M226: 클라뷰 | N226: USD | O226: 200 | P226: 3.03 | Q226: 606.00 | R226: 0.00 | S226: 870,216.00 | T226: 65.93 | U226: 13,185.45 | V226: 857,030.55 | X226: 98.5 | Y226: IN00441297 | AA226: =LEFT(E226,7) -> 2026-06 | AB226: =IF(AND($AA226>="2025-01",$AA226<="2025-06"),"H1_2025",IF(AND($AA226>="2026-01",$AA226<="2026-06"),"H1_2026","")) -> H1_2026 | AC226: =IFERROR(VALUE(SUBSTITUTE(S226,",","")),0) -> 870216 | AD226: =IFERROR(VALUE(SUBSTITUTE(O226,",","")),0) -> 200 | AE226: =IFERROR(VALUE(SUBSTITUTE(V226,",","")),0) -> 857030.55 | AF226: =IF(ISNUMBER(SEARCH("FOC",W226)),"FOC",IF(ISNUMBER(SEARCH("샘플",W226)),"Sample","Paid")) -> Paid
A227: 225 | B227: 06312 | C227: KR | D227: OPO | E227: 2026-06-08 | F227: minju | G227: MOARS | I227: Netherlands The | J227: KR-OVERSEAS | K227: MECUP10-PKR | L227: 콜라겐 나이트 랩핑 마스크 75ml | M227: 메디큐브 | N227: USD | O227: 200 | P227: 8.35 | Q227: 1,670.00 | R227: 0.00 | S227: 2,398,120.00 | T227: 10,260.00 | U227: 2,052,000.00 | V227: 346,120.00 | X227: 14.4 | Y227: IN00441297 | AA227: =LEFT(E227,7) -> 2026-06 | AB227: =IF(AND($AA227>="2025-01",$AA227<="2025-06"),"H1_2025",IF(AND($AA227>="2026-01",$AA227<="2026-06"),"H1_2026","")) -> H1_2026 | AC227: =IFERROR(VALUE(SUBSTITUTE(S227,",","")),0) -> 2398120 | AD227: =IFERROR(VALUE(SUBSTITUTE(O227,",","")),0) -> 200 | AE227: =IFERROR(VALUE(SUBSTITUTE(V227,",","")),0) -> 346120 | AF227: =IF(ISNUMBER(SEARCH("FOC",W227)),"FOC",IF(ISNUMBER(SEARCH("샘플",W227)),"Sample","Paid")) -> Paid
A228: 226 | B228: 06312 | C228: KR | D228: OPO | E228: 2026-06-08 | F228: minju | G228: MOARS | I228: Netherlands The | J228: KR-OVERSEAS | K228: PRS07-TPD | L228: (통합) 오트 피디알엔 젠틀 리파이닝 토너 200ml | M228: 퓨리토 서울 | N228: USD | O228: 200 | P228: 5.68 | Q228: 1,136.00 | R228: 0.00 | S228: 1,631,296.00 | T228: 8,909.09 | U228: 1,781,818.00 | V228: -150,522.00 | X228: -9.2 | Y228: IN00441297 | AA228: =LEFT(E228,7) -> 2026-06 | AB228: =IF(AND($AA228>="2025-01",$AA228<="2025-06"),"H1_2025",IF(AND($AA228>="2026-01",$AA228<="2026-06"),"H1_2026","")) -> H1_2026 | AC228: =IFERROR(VALUE(SUBSTITUTE(S228,",","")),0) -> 1631296 | AD228: =IFERROR(VALUE(SUBSTITUTE(O228,",","")),0) -> 200 | AE228: =IFERROR(VALUE(SUBSTITUTE(V228,",","")),0) -> -150522 | AF228: =IF(ISNUMBER(SEARCH("FOC",W228)),"FOC",IF(ISNUMBER(SEARCH("샘플",W228)),"Sample","Paid")) -> Paid
A229: 227 | B229: 06312 | C229: KR | D229: OPO | E229: 2026-06-08 | F229: minju | G229: MOARS | I229: Netherlands The | J229: KR-OVERSEAS | K229: PYS01-IBTR | L229: *리뉴얼 블랙티 타임 리버스 아이크림 25ml | M229: 편강율 | N229: USD | O229: 200 | P229: 9.75 | Q229: 1,950.00 | R229: 0.00 | S229: 2,800,200.00 | T229: 12,000.00 | U229: 2,400,000.00 | V229: 400,200.00 | X229: 14.3 | Y229: IN00441297 | AA229: =LEFT(E229,7) -> 2026-06 | AB229: =IF(AND($AA229>="2025-01",$AA229<="2025-06"),"H1_2025",IF(AND($AA229>="2026-01",$AA229<="2026-06"),"H1_2026","")) -> H1_2026 | AC229: =IFERROR(VALUE(SUBSTITUTE(S229,",","")),0) -> 2800200 | AD229: =IFERROR(VALUE(SUBSTITUTE(O229,",","")),0) -> 200 | AE229: =IFERROR(VALUE(SUBSTITUTE(V229,",","")),0) -> 400200 | AF229: =IF(ISNUMBER(SEARCH("FOC",W229)),"FOC",IF(ISNUMBER(SEARCH("샘플",W229)),"Sample","Paid")) -> Paid
A230: 228 | B230: 06312 | C230: KR | D230: OPO | E230: 2026-06-04 | F230: minju | G230: MOARS | I230: Netherlands The | J230: KR-OVERSEAS | K230: cosC02-Fr | L230: 어드벤스드 스네일 뮤신 젤 클렌저 150ml_일원화 | M230: 코스알엑스 | N230: USD | O230: 360 | P230: 6.11 | Q230: 2,199.60 | R230: 0.00 | S230: 3,241,110.60 | T230: 6,660.00 | U230: 2,397,600.00 | V230: 843,510.60 | X230: 26.0 | Y230: IN00443088 | AA230: =LEFT(E230,7) -> 2026-06 | AB230: =IF(AND($AA230>="2025-01",$AA230<="2025-06"),"H1_2025",IF(AND($AA230>="2026-01",$AA230<="2026-06"),"H1_2026","")) -> H1_2026 | AC230: =IFERROR(VALUE(SUBSTITUTE(S230,",","")),0) -> 3241110.6 | AD230: =IFERROR(VALUE(SUBSTITUTE(O230,",","")),0) -> 360 | AE230: =IFERROR(VALUE(SUBSTITUTE(V230,",","")),0) -> 843510.6 | AF230: =IF(ISNUMBER(SEARCH("FOC",W230)),"FOC",IF(ISNUMBER(SEARCH("샘플",W230)),"Sample","Paid")) -> Paid
A231: 229 | B231: 06312 | C231: KR | D231: OPO | E231: 2026-06-04 | F231: minju | G231: MOARS | I231: Netherlands The | J231: KR-OVERSEAS | K231: cosC05-Gelr | L231: 약산성 굿모닝 젤 클렌져 150ml_일원화 | M231: 코스알엑스 | N231: USD | O231: 84 | P231: 3.36 | Q231: 282.24 | R231: 0.00 | S231: 415,880.64 | T231: 3,663.00 | U231: 307,692.00 | V231: 108,188.64 | X231: 26.0 | Y231: IN00443088 | AA231: =LEFT(E231,7) -> 2026-06 | AB231: =IF(AND($AA231>="2025-01",$AA231<="2025-06"),"H1_2025",IF(AND($AA231>="2026-01",$AA231<="2026-06"),"H1_2026","")) -> H1_2026 | AC231: =IFERROR(VALUE(SUBSTITUTE(S231,",","")),0) -> 415880.64 | AD231: =IFERROR(VALUE(SUBSTITUTE(O231,",","")),0) -> 84 | AE231: =IFERROR(VALUE(SUBSTITUTE(V231,",","")),0) -> 108188.64 | AF231: =IF(ISNUMBER(SEARCH("FOC",W231)),"FOC",IF(ISNUMBER(SEARCH("샘플",W231)),"Sample","Paid")) -> Paid
A232: 230 | B232: 06312 | C232: KR | D232: OPO | E232: 2026-06-04 | F232: minju | G232: MOARS | I232: Netherlands The | J232: KR-OVERSEAS | K232: cosC05-OCr | L232: 약산성 나이아신아마이드 미셀라 클렌징 워터 400ml_일원화 | M232: 코스알엑스 | N232: USD | O232: 150 | P232: 4.41 | Q232: 661.50 | R232: 0.00 | S232: 974,720.25 | T232: 4,810.00 | U232: 721,500.00 | V232: 253,220.25 | X232: 26.0 | Y232: IN00443088 | AA232: =LEFT(E232,7) -> 2026-06 | AB232: =IF(AND($AA232>="2025-01",$AA232<="2025-06"),"H1_2025",IF(AND($AA232>="2026-01",$AA232<="2026-06"),"H1_2026","")) -> H1_2026 | AC232: =IFERROR(VALUE(SUBSTITUTE(S232,",","")),0) -> 974720.25 | AD232: =IFERROR(VALUE(SUBSTITUTE(O232,",","")),0) -> 150 | AE232: =IFERROR(VALUE(SUBSTITUTE(V232,",","")),0) -> 253220.25 | AF232: =IF(ISNUMBER(SEARCH("FOC",W232)),"FOC",IF(ISNUMBER(SEARCH("샘플",W232)),"Sample","Paid")) -> Paid
A233: 231 | B233: 06312 | C233: KR | D233: OPO | E233: 2026-06-04 | F233: minju | G233: MOARS | I233: Netherlands The | J233: KR-OVERSEAS | K233: cosP90-M1 | L233: (1EA) 5 피디알엔 히알루론산 바이탈 하이드레이팅 하이드로겔 마스크 | M233: 코스알엑스 | N233: USD | O233: 900 | P233: 2.04 | Q233: 1,836.00 | R233: 0.00 | S233: 2,705,346.00 | T233: 2,400.00 | U233: 2,160,000.00 | V233: 545,346.00 | X233: 20.2 | Y233: IN00443088 | AA233: =LEFT(E233,7) -> 2026-06 | AB233: =IF(AND($AA233>="2025-01",$AA233<="2025-06"),"H1_2025",IF(AND($AA233>="2026-01",$AA233<="2026-06"),"H1_2026","")) -> H1_2026 | AC233: =IFERROR(VALUE(SUBSTITUTE(S233,",","")),0) -> 2705346 | AD233: =IFERROR(VALUE(SUBSTITUTE(O233,",","")),0) -> 900 | AE233: =IFERROR(VALUE(SUBSTITUTE(V233,",","")),0) -> 545346 | AF233: =IF(ISNUMBER(SEARCH("FOC",W233)),"FOC",IF(ISNUMBER(SEARCH("샘플",W233)),"Sample","Paid")) -> Paid
A234: 232 | B234: 06312 | C234: KR | D234: OPO | E234: 2026-06-04 | F234: minju | G234: MOARS | I234: Netherlands The | J234: KR-OVERSEAS | K234: cosS02-Cr | L234: 어드벤스드 스네일 92 올인원 크림 100g_일원화 | M234: 코스알엑스 | N234: USD | O234: 1,960 | P234: 6.45 | Q234: 12,642.00 | R234: 0.00 | S234: 18,627,987.00 | T234: 7,030.00 | U234: 13,778,800.00 | V234: 4,849,187.00 | X234: 26.0 | Y234: IN00443088 | AA234: =LEFT(E234,7) -> 2026-06 | AB234: =IF(AND($AA234>="2025-01",$AA234<="2025-06"),"H1_2025",IF(AND($AA234>="2026-01",$AA234<="2026-06"),"H1_2026","")) -> H1_2026 | AC234: =IFERROR(VALUE(SUBSTITUTE(S234,",","")),0) -> 18627987 | AD234: =IFERROR(VALUE(SUBSTITUTE(O234,",","")),0) -> 1960 | AE234: =IFERROR(VALUE(SUBSTITUTE(V234,",","")),0) -> 4849187 | AF234: =IF(ISNUMBER(SEARCH("FOC",W234)),"FOC",IF(ISNUMBER(SEARCH("샘플",W234)),"Sample","Paid")) -> Paid
A235: 233 | B235: 06312 | C235: KR | D235: OPO | E235: 2026-06-04 | F235: minju | G235: MOARS | I235: Netherlands The | J235: KR-OVERSEAS | K235: cosS02-Er | L235: 어드벤스드 스네일 펩타이드 아이 크림 25ml_일원화 | M235: 코스알엑스 | N235: USD | O235: 198 | P235: 8.48 | Q235: 1,679.04 | R235: 0.00 | S235: 2,474,065.44 | T235: 9,250.00 | U235: 1,831,500.00 | V235: 642,565.44 | X235: 26.0 | Y235: IN00443088 | AA235: =LEFT(E235,7) -> 2026-06 | AB235: =IF(AND($AA235>="2025-01",$AA235<="2025-06"),"H1_2025",IF(AND($AA235>="2026-01",$AA235<="2026-06"),"H1_2026","")) -> H1_2026 | AC235: =IFERROR(VALUE(SUBSTITUTE(S235,",","")),0) -> 2474065.4 | AD235: =IFERROR(VALUE(SUBSTITUTE(O235,",","")),0) -> 198 | AE235: =IFERROR(VALUE(SUBSTITUTE(V235,",","")),0) -> 642565.44 | AF235: =IF(ISNUMBER(SEARCH("FOC",W235)),"FOC",IF(ISNUMBER(SEARCH("샘플",W235)),"Sample","Paid")) -> Paid
... A1289: 1287 | B1289: 06312 | C1289: KR | D1289: OPO | E1289: 2026-02-06 | F1289: erine | G1289: MOARS | I1289: Netherlands The | J1289: KR-OVERSEAS | K1289: FLS001-C03 | L1289: 레티놀 0.3% 크림 20ml | M1289: 프랭클리 | N1289: USD | O1289: 60 | P1289: 6.48 | Q1289: 388.80 | R1289: 0.00 | S1289: 543,775.68 | T1289: 5,500.00 | U1289: 330,000.00 | V1289: 213,775.68 | X1289: 39.3 | Y1289: IN00409829 | AA1289: =LEFT(E1289,7) -> 2026-02 | AB1289: =IF(AND($AA1289>="2025-01",$AA1289<="2025-06"),"H1_2025",IF(AND($AA1289>="2026-01",$AA1289<="2026-06"),"H1_2026","")) -> H1_2026 | AC1289: =IFERROR(VALUE(SUBSTITUTE(S1289,",","")),0) -> 543775.68 | AD1289: =IFERROR(VALUE(SUBSTITUTE(O1289,",","")),0) -> 60 | AE1289: =IFERROR(VALUE(SUBSTITUTE(V1289,",","")),0) -> 213775.68 | AF1289: =IF(ISNUMBER(SEARCH("FOC",W1289)),"FOC",IF(ISNUMBER(SEARCH("샘플",W1289)),"Sample","Paid")) -> Paid
A1290: 1288 | B1290: 06312 | C1290: KR | D1290: OPO | E1290: 2026-02-06 | F1290: erine | G1290: MOARS | I1290: Netherlands The | J1290: KR-OVERSEAS | K1290: FLS003-SFOC | L1290: (B2B 영업용 FOC) 클로저 세럼 30ml | M1290: 프랭클리 | N1290: USD | O1290: 1 | P1290: 0.01 | Q1290: 0.01 | R1290: 0.00 | S1290: 13.99 | T1290: 0.00 | U1290: 0.00 | V1290: 13.99 | W1290: 상품 샘플링 (견본,무상증정) | X1290: 100.0 | Y1290: IN00409829 | AA1290: =LEFT(E1290,7) -> 2026-02 | AB1290: =IF(AND($AA1290>="2025-01",$AA1290<="2025-06"),"H1_2025",IF(AND($AA1290>="2026-01",$AA1290<="2026-06"),"H1_2026","")) -> H1_2026 | AC1290: =IFERROR(VALUE(SUBSTITUTE(S1290,",","")),0) -> 13.99 | AD1290: =IFERROR(VALUE(SUBSTITUTE(O1290,",","")),0) -> 1 | AE1290: =IFERROR(VALUE(SUBSTITUTE(V1290,",","")),0) -> 13.99 | AF1290: =IF(ISNUMBER(SEARCH("FOC",W1290)),"FOC",IF(ISNUMBER(SEARCH("샘플",W1290)),"Sample","Paid")) -> Sample
A1291: 1289 | B1291: 06312 | C1291: KR | D1291: OPO | E1291: 2026-02-06 | F1291: erine | G1291: MOARS | I1291: Netherlands The | J1291: KR-OVERSEAS | K1291: G9C07-G | L1291: 자몽 비타 필링젤 150ml | M1291: 지나인(G9) | N1291: USD | O1291: 6 | P1291: 3.65 | Q1291: 21.90 | R1291: 0.00 | S1291: 30,629.34 | T1291: 3,818.18 | U1291: 22,909.09 | V1291: 7,720.25 | X1291: 25.2 | Y1291: IN00409829 | AA1291: =LEFT(E1291,7) -> 2026-02 | AB1291: =IF(AND($AA1291>="2025-01",$AA1291<="2025-06"),"H1_2025",IF(AND($AA1291>="2026-01",$AA1291<="2026-06"),"H1_2026","")) -> H1_2026 | AC1291: =IFERROR(VALUE(SUBSTITUTE(S1291,",","")),0) -> 30629.34 | AD1291: =IFERROR(VALUE(SUBSTITUTE(O1291,",","")),0) -> 6 | AE1291: =IFERROR(VALUE(SUBSTITUTE(V1291,",","")),0) -> 7720.25 | AF1291: =IF(ISNUMBER(SEARCH("FOC",W1291)),"FOC",IF(ISNUMBER(SEARCH("샘플",W1291)),"Sample","Paid")) -> Paid
A1292: 1290 | B1292: 06312 | C1292: KR | D1292: OPO | E1292: 2026-02-06 | F1292: erine | G1292: MOARS | I1292: Netherlands The | J1292: KR-OVERSEAS | K1292: G9P12-MR | L1292: [5매입]셀프 에스테틱 로즈 하이드로겔 립 패치 | M1292: 지나인(G9) | N1292: USD | O1292: 60 | P1292: 4.29 | Q1292: 257.40 | R1292: 0.00 | S1292: 359,999.64 | T1292: 4,819.00 | U1292: 289,140.00 | V1292: 70,859.64 | X1292: 19.7 | Y1292: IN00409829 | AA1292: =LEFT(E1292,7) -> 2026-02 | AB1292: =IF(AND($AA1292>="2025-01",$AA1292<="2025-06"),"H1_2025",IF(AND($AA1292>="2026-01",$AA1292<="2026-06"),"H1_2026","")) -> H1_2026 | AC1292: =IFERROR(VALUE(SUBSTITUTE(S1292,",","")),0) -> 359999.64 | AD1292: =IFERROR(VALUE(SUBSTITUTE(O1292,",","")),0) -> 60 | AE1292: =IFERROR(VALUE(SUBSTITUTE(V1292,",","")),0) -> 70859.64 | AF1292: =IF(ISNUMBER(SEARCH("FOC",W1292)),"FOC",IF(ISNUMBER(SEARCH("샘플",W1292)),"Sample","Paid")) -> Paid
A1293: 1291 | B1293: 06312 | C1293: KR | D1293: OPO | E1293: 2026-02-06 | F1293: erine | G1293: MOARS | I1293: Netherlands The | J1293: KR-OVERSEAS | K1293: HMCM1-DSSMBBV | L1293: (리뉴얼) 데일리즘 스머지 스탑 마스카라 볼륨 브라운 | M1293: 헤이미쉬 | N1293: USD | O1293: 30 | P1293: 3.80 | Q1293: 114.00 | R1293: 0.00 | S1293: 159,440.40 | T1293: 0.00 | U1293: 0.00 | V1293: 159,440.40 | X1293: 100.0 | Y1293: IN00409829 | AA1293: =LEFT(E1293,7) -> 2026-02 | AB1293: =IF(AND($AA1293>="2025-01",$AA1293<="2025-06"),"H1_2025",IF(AND($AA1293>="2026-01",$AA1293<="2026-06"),"H1_2026","")) -> H1_2026 | AC1293: =IFERROR(VALUE(SUBSTITUTE(S1293,",","")),0) -> 159440.4 | AD1293: =IFERROR(VALUE(SUBSTITUTE(O1293,",","")),0) -> 30 | AE1293: =IFERROR(VALUE(SUBSTITUTE(V1293,",","")),0) -> 159440.4 | AF1293: =IF(ISNUMBER(SEARCH("FOC",W1293)),"FOC",IF(ISNUMBER(SEARCH("샘플",W1293)),"Sample","Paid")) -> Paid
A1294: 1292 | B1294: 06312 | C1294: KR | D1294: OPO | E1294: 2026-02-06 | F1294: erine | G1294: MOARS | I1294: Netherlands The | J1294: KR-OVERSEAS | K1294: HMCM1-DSSMV | L1294: (리뉴얼) 데일리즘 스머지 스탑 마스카라 볼륨 블랙 | M1294: 헤이미쉬 | N1294: USD | O1294: 140 | P1294: 3.80 | Q1294: 532.00 | R1294: 0.00 | S1294: 744,055.20 | T1294: 3,691.00 | U1294: 516,740.00 | V1294: 227,315.20 | X1294: 30.6 | Y1294: IN00409829 | AA1294: =LEFT(E1294,7) -> 2026-02 | AB1294: =IF(AND($AA1294>="2025-01",$AA1294<="2025-06"),"H1_2025",IF(AND($AA1294>="2026-01",$AA1294<="2026-06"),"H1_2026","")) -> H1_2026 | AC1294: =IFERROR(VALUE(SUBSTITUTE(S1294,",","")),0) -> 744055.2 | AD1294: =IFERROR(VALUE(SUBSTITUTE(O1294,",","")),0) -> 140 | AE1294: =IFERROR(VALUE(SUBSTITUTE(V1294,",","")),0) -> 227315.2 | AF1294: =IF(ISNUMBER(SEARCH("FOC",W1294)),"FOC",IF(ISNUMBER(SEARCH("샘플",W1294)),"Sample","Paid")) -> Paid
A1295: 1293 | B1295: 06312 | C1295: KR | D1295: OPO | E1295: 2026-02-06 | F1295: erine | G1295: MOARS | I1295: Netherlands The | J1295: KR-OVERSEAS | K1295: HMS09-REP60 | L1295: (리뉴얼 예정)불가리안 로즈 하이드로겔 아이패치 60매 | M1295: 헤이미쉬 | N1295: USD | O1295: 290 | P1295: 5.43 | Q1295: 1,574.70 | R1295: 0.00 | S1295: 2,202,375.42 | T1295: 5,272.73 | U1295: 1,529,090.89 | V1295: 673,284.53 | X1295: 30.6 | Y1295: IN00409829 | AA1295: =LEFT(E1295,7) -> 2026-02 | AB1295: =IF(AND($AA1295>="2025-01",$AA1295<="2025-06"),"H1_2025",IF(AND($AA1295>="2026-01",$AA1295<="2026-06"),"H1_2026","")) -> H1_2026 | AC1295: =IFERROR(VALUE(SUBSTITUTE(S1295,",","")),0) -> 2202375.4 | AD1295: =IFERROR(VALUE(SUBSTITUTE(O1295,",","")),0) -> 290 | AE1295: =IFERROR(VALUE(SUBSTITUTE(V1295,",","")),0) -> 673284.53 | AF1295: =IF(ISNUMBER(SEARCH("FOC",W1295)),"FOC",IF(ISNUMBER(SEARCH("샘플",W1295)),"Sample","Paid")) -> Paid
A1296: 1294 | B1296: 06312 | C1296: KR | D1296: OPO | E1296: 2026-02-06 | F1296: erine | G1296: MOARS | I1296: Netherlands The | J1296: KR-OVERSEAS | K1296: IDCP02-PKms | L1296: 미니 스쿱스 15ml, 3ea | M1296: 아이듀케어 | N1296: USD | O1296: 20 | P1296: 8.24 | Q1296: 164.80 | R1296: 0.00 | S1296: 230,489.28 | T1296: 8,706.00 | U1296: 174,120.00 | V1296: 56,369.28 | X1296: 24.5 | Y1296: IN00409829 | AA1296: =LEFT(E1296,7) -> 2026-02 | AB1296: =IF(AND($AA1296>="2025-01",$AA1296<="2025-06"),"H1_2025",IF(AND($AA1296>="2026-01",$AA1296<="2026-06"),"H1_2026","")) -> H1_2026 | AC1296: =IFERROR(VALUE(SUBSTITUTE(S1296,",","")),0) -> 230489.28 | AD1296: =IFERROR(VALUE(SUBSTITUTE(O1296,",","")),0) -> 20 | AE1296: =IFERROR(VALUE(SUBSTITUTE(V1296,",","")),0) -> 56369.28 | AF1296: =IF(ISNUMBER(SEARCH("FOC",W1296)),"FOC",IF(ISNUMBER(SEARCH("샘플",W1296)),"Sample","Paid")) -> Paid
A1297: 1295 | B1297: 06312 | C1297: KR | D1297: OPO | E1297: 2026-02-06 | F1297: erine | G1297: MOARS | I1297: Netherlands The | J1297: KR-OVERSEAS | K1297: IDCP06-A | L1297: 쥬시 키튼 30ml | M1297: 아이듀케어 | N1297: USD | O1297: 10 | P1297: 9.95 | Q1297: 99.50 | R1297: 0.00 | S1297: 139,160.70 | T1297: 10,882.00 | U1297: 108,820.00 | V1297: 30,340.70 | X1297: 21.8 | Y1297: IN00409829 | AA1297: =LEFT(E1297,7) -> 2026-02 | AB1297: =IF(AND($AA1297>="2025-01",$AA1297<="2025-06"),"H1_2025",IF(AND($AA1297>="2026-01",$AA1297<="2026-06"),"H1_2026","")) -> H1_2026 | AC1297: =IFERROR(VALUE(SUBSTITUTE(S1297,",","")),0) -> 139160.7 | AD1297: =IFERROR(VALUE(SUBSTITUTE(O1297,",","")),0) -> 10 | AE1297: =IFERROR(VALUE(SUBSTITUTE(V1297,",","")),0) -> 30340.7 | AF1297: =IF(ISNUMBER(SEARCH("FOC",W1297)),"FOC",IF(ISNUMBER(SEARCH("샘플",W1297)),"Sample","Paid")) -> Paid
A1298: 1296 | B1298: 06312 | C1298: KR | D1298: OPO | E1298: 2026-02-06 | F1298: erine | G1298: MOARS | I1298: Netherlands The | J1298: KR-OVERSEAS | K1298: MECUC01-RF | L1298: 레드 폼 클렌저 2020 120ml | M1298: 메디큐브 | N1298: USD | O1298: 80 | P1298: 6.22 | Q1298: 497.60 | R1298: 0.00 | S1298: 695,943.36 | T1298: 5,500.00 | U1298: 440,000.00 | V1298: 255,943.36 | X1298: 36.8 | Y1298: IN00409829 | AA1298: =LEFT(E1298,7) -> 2026-02 | AB1298: =IF(AND($AA1298>="2025-01",$AA1298<="2025-06"),"H1_2025",IF(AND($AA1298>="2026-01",$AA1298<="2026-06"),"H1_2026","")) -> H1_2026 | AC1298: =IFERROR(VALUE(SUBSTITUTE(S1298,",","")),0) -> 695943.36 | AD1298: =IFERROR(VALUE(SUBSTITUTE(O1298,",","")),0) -> 80 | AE1298: =IFERROR(VALUE(SUBSTITUTE(V1298,",","")),0) -> 255943.36 | AF1298: =IF(ISNUMBER(SEARCH("FOC",W1298)),"FOC",IF(ISNUMBER(SEARCH("샘플",W1298)),"Sample","Paid")) -> Paid
A1299: 1297 | B1299: 06312 | C1299: KR | D1299: OPO | E1299: 2026-02-06 | F1299: erine | G1299: MOARS | I1299: Netherlands The | J1299: KR-OVERSEAS | K1299: MECUC08-F | L1299: 제로 폼 클렌저 120g | M1299: 메디큐브 | N1299: USD | O1299: 390 | P1299: 6.22 | Q1299: 2,425.80 | R1299: 0.00 | S1299: 3,392,723.88 | T1299: 6,500.00 | U1299: 2,535,000.00 | V1299: 857,723.88 | X1299: 25.3 | Y1299: IN00409829 | AA1299: =LEFT(E1299,7) -> 2026-02 | AB1299: =IF(AND($AA1299>="2025-01",$AA1299<="2025-06"),"H1_2025",IF(AND($AA1299>="2026-01",$AA1299<="2026-06"),"H1_2026","")) -> H1_2026 | AC1299: =IFERROR(VALUE(SUBSTITUTE(S1299,",","")),0) -> 3392723.9 | AD1299: =IFERROR(VALUE(SUBSTITUTE(O1299,",","")),0) -> 390 | AE1299: =IFERROR(VALUE(SUBSTITUTE(V1299,",","")),0) -> 857723.88 | AF1299: =IF(ISNUMBER(SEARCH("FOC",W1299)),"FOC",IF(ISNUMBER(SEARCH("샘플",W1299)),"Sample","Paid")) -> Paid
A1300: 1298 | B1300: 06312 | C1300: KR | D1300: OPO | E1300: 2026-02-06 | F1300: erine | G1300: MOARS | I1300: Netherlands The | J1300: KR-OVERSEAS | K1300: MECUP10-PKR | L1300: 콜라겐 나이트 랩핑 마스크 75ml | M1300: 메디큐브 | N1300: USD | O1300: 750 | P1300: 9.19 | Q1300: 6,892.50 | R1300: 0.00 | S1300: 9,639,850.50 | T1300: 10,260.00 | U1300: 7,695,000.00 | V1300: 1,944,850.50 | X1300: 20.2 | Y1300: IN00409829 | AA1300: =LEFT(E1300,7) -> 2026-02 | AB1300: =IF(AND($AA1300>="2025-01",$AA1300<="2025-06"),"H1_2025",IF(AND($AA1300>="2026-01",$AA1300<="2026-06"),"H1_2026","")) -> H1_2026 | AC1300: =IFERROR(VALUE(SUBSTITUTE(S1300,",","")),0) -> 9639850.5 | AD1300: =IFERROR(VALUE(SUBSTITUTE(O1300,",","")),0) -> 750 | AE1300: =IFERROR(VALUE(SUBSTITUTE(V1300,",","")),0) -> 1944850.5 | AF1300: =IF(ISNUMBER(SEARCH("FOC",W1300)),"FOC",IF(ISNUMBER(SEARCH("샘플",W1300)),"Sample","Paid")) -> Paid
A1301: 1299 | B1301: 06312 | C1301: KR | D1301: OPO | E1301: 2026-02-06 | F1301: erine | G1301: MOARS | I1301: Netherlands The | J1301: KR-OVERSEAS | K1301: MECUS01-RS | L1301: 레드 세럼 2.0_NEW 30ml | M1301: 메디큐브 | N1301: USD | O1301: 20 | P1301: 6.20 | Q1301: 124.00 | R1301: 0.00 | S1301: 173,426.40 | T1301: 6,960.00 | U1301: 139,200.00 | V1301: 34,226.40 | X1301: 19.7 | Y1301: IN00409829 | AA1301: =LEFT(E1301,7) -> 2026-02 | AB1301: =IF(AND($AA1301>="2025-01",$AA1301<="2025-06"),"H1_2025",IF(AND($AA1301>="2026-01",$AA1301<="2026-06"),"H1_2026","")) -> H1_2026 | AC1301: =IFERROR(VALUE(SUBSTITUTE(S1301,",","")),0) -> 173426.4 | AD1301: =IFERROR(VALUE(SUBSTITUTE(O1301,",","")),0) -> 20 | AE1301: =IFERROR(VALUE(SUBSTITUTE(V1301,",","")),0) -> 34226.4 | AF1301: =IF(ISNUMBER(SEARCH("FOC",W1301)),"FOC",IF(ISNUMBER(SEARCH("샘플",W1301)),"Sample","Paid")) -> Paid
A1302: 1300 | B1302: 06312 | C1302: KR | D1302: OPO | E1302: 2026-02-06 | F1302: erine | G1302: MOARS | I1302: Netherlands The | J1302: KR-OVERSEAS | K1302: MECUS01-RT | L1302: 레드 토너 2.0_NEW 100ml | M1302: 메디큐브 | N1302: USD | O1302: 40 | P1302: 7.21 | Q1302: 288.40 | R1302: 0.00 | S1302: 403,356.24 | T1302: 8,000.00 | U1302: 320,000.00 | V1302: 83,356.24 | X1302: 20.7 | Y1302: IN00409829 | AA1302: =LEFT(E1302,7) -> 2026-02 | AB1302: =IF(AND($AA1302>="2025-01",$AA1302<="2025-06"),"H1_2025",IF(AND($AA1302>="2026-01",$AA1302<="2026-06"),"H1_2026","")) -> H1_2026 | AC1302: =IFERROR(VALUE(SUBSTITUTE(S1302,",","")),0) -> 403356.24 | AD1302: =IFERROR(VALUE(SUBSTITUTE(O1302,",","")),0) -> 40 | AE1302: =IFERROR(VALUE(SUBSTITUTE(V1302,",","")),0) -> 83356.24 | AF1302: =IF(ISNUMBER(SEARCH("FOC",W1302)),"FOC",IF(ISNUMBER(SEARCH("샘플",W1302)),"Sample","Paid")) -> Paid
... A1360: 1358 | B1360: 06312 | C1360: KR | D1360: OPO | E1360: 2026-02-04 | F1360: erine | G1360: MOARS | I1360: Netherlands The | J1360: KR-OVERSEAS | K1360: JSMSM03-SS | L1360: (단종)인삼선세럼 50ml | M1360: 조선미녀 | N1360: USD | O1360: 90 | P1360: 7.29 | Q1360: 656.10 | R1360: 0.00 | S1360: 926,938.08 | T1360: 8,820.00 | U1360: 793,800.00 | V1360: 133,138.08 | X1360: 14.4 | Y1360: IN00408995 | AA1360: =LEFT(E1360,7) -> 2026-02 | AB1360: =IF(AND($AA1360>="2025-01",$AA1360<="2025-06"),"H1_2025",IF(AND($AA1360>="2026-01",$AA1360<="2026-06"),"H1_2026","")) -> H1_2026 | AC1360: =IFERROR(VALUE(SUBSTITUTE(S1360,",","")),0) -> 926938.08 | AD1360: =IFERROR(VALUE(SUBSTITUTE(O1360,",","")),0) -> 90 | AE1360: =IFERROR(VALUE(SUBSTITUTE(V1360,",","")),0) -> 133138.08 | AF1360: =IF(ISNUMBER(SEARCH("FOC",W1360)),"FOC",IF(ISNUMBER(SEARCH("샘플",W1360)),"Sample","Paid")) -> Paid
A1361: 1359 | B1361: 06312 | C1361: KR | D1361: OPO | E1361: 2026-02-04 | F1361: erine | G1361: MOARS | I1361: Netherlands The | J1361: KR-OVERSEAS | K1361: NRHS01-KHD | L1361: 코어 리빌드 하드 픽스 헤어 마스카라 | M1361: 나르카 | N1361: USD | O1361: 10 | P1361: 0.01 | Q1361: 0.10 | R1361: 0.00 | S1361: 141.28 | T1361: 6,143.64 | U1361: 61,436.36 | V1361: -61,295.08 | W1361: 상품 샘플링 (견본,무상증정) | X1361: -43,385.5 | Y1361: IN00408995 | AA1361: =LEFT(E1361,7) -> 2026-02 | AB1361: =IF(AND($AA1361>="2025-01",$AA1361<="2025-06"),"H1_2025",IF(AND($AA1361>="2026-01",$AA1361<="2026-06"),"H1_2026","")) -> H1_2026 | AC1361: =IFERROR(VALUE(SUBSTITUTE(S1361,",","")),0) -> 141.28 | AD1361: =IFERROR(VALUE(SUBSTITUTE(O1361,",","")),0) -> 10 | AE1361: =IFERROR(VALUE(SUBSTITUTE(V1361,",","")),0) -> -61295.08 | AF1361: =IF(ISNUMBER(SEARCH("FOC",W1361)),"FOC",IF(ISNUMBER(SEARCH("샘플",W1361)),"Sample","Paid")) -> Sample
A1362: 1360 | B1362: 06312 | C1362: KR | D1362: OPO | E1362: 2026-02-04 | F1362: erine | G1362: MOARS | I1362: Netherlands The | J1362: KR-OVERSEAS | K1362: NRHS01-S70 | L1362: (단종) 코어 리빌드 젠틀 새틴 헤어 에센스 70ml | M1362: 나르카 | N1362: USD | O1362: 10 | P1362: 0.01 | Q1362: 0.10 | R1362: 0.00 | S1362: 141.28 | T1362: 9,807.27 | U1362: 98,072.73 | V1362: -97,931.45 | W1362: 상품 샘플링 (견본,무상증정) | X1362: -69,317.3 | Y1362: IN00408995 | AA1362: =LEFT(E1362,7) -> 2026-02 | AB1362: =IF(AND($AA1362>="2025-01",$AA1362<="2025-06"),"H1_2025",IF(AND($AA1362>="2026-01",$AA1362<="2026-06"),"H1_2026","")) -> H1_2026 | AC1362: =IFERROR(VALUE(SUBSTITUTE(S1362,",","")),0) -> 141.28 | AD1362: =IFERROR(VALUE(SUBSTITUTE(O1362,",","")),0) -> 10 | AE1362: =IFERROR(VALUE(SUBSTITUTE(V1362,",","")),0) -> -97931.45 | AF1362: =IF(ISNUMBER(SEARCH("FOC",W1362)),"FOC",IF(ISNUMBER(SEARCH("샘플",W1362)),"Sample","Paid")) -> Sample
A1363: 1361 | B1363: 06312 | C1363: KR | D1363: OPO | E1363: 2026-02-04 | F1363: erine | G1363: MOARS | I1363: Netherlands The | J1363: KR-OVERSEAS | K1363: NRHS01-TTHM | L1363: 코어 리빌드 스트레이트 슬릭 헤어 밀크 150ml | M1363: 나르카 | N1363: USD | O1363: 10 | P1363: 0.01 | Q1363: 0.10 | R1363: 0.00 | S1363: 141.28 | T1363: 6,545.45 | U1363: 65,454.55 | V1363: -65,313.26 | W1363: 상품 샘플링 (견본,무상증정) | X1363: -46,229.7 | Y1363: IN00408995 | AA1363: =LEFT(E1363,7) -> 2026-02 | AB1363: =IF(AND($AA1363>="2025-01",$AA1363<="2025-06"),"H1_2025",IF(AND($AA1363>="2026-01",$AA1363<="2026-06"),"H1_2026","")) -> H1_2026 | AC1363: =IFERROR(VALUE(SUBSTITUTE(S1363,",","")),0) -> 141.28 | AD1363: =IFERROR(VALUE(SUBSTITUTE(O1363,",","")),0) -> 10 | AE1363: =IFERROR(VALUE(SUBSTITUTE(V1363,",","")),0) -> -65313.26 | AF1363: =IF(ISNUMBER(SEARCH("FOC",W1363)),"FOC",IF(ISNUMBER(SEARCH("샘플",W1363)),"Sample","Paid")) -> Sample
A1364: 1362 | B1364: 06312 | C1364: KR | D1364: OPO | E1364: 2026-02-04 | F1364: erine | G1364: MOARS | I1364: Netherlands The | J1364: KR-OVERSEAS | K1364: RjAS01-CREU | L1364: [EU] 어드밴스드 PDRN 크림 20ml | M1364: 닥터 리쥬올 | N1364: USD | O1364: 50 | P1364: 0.01 | Q1364: 0.50 | R1364: 0.00 | S1364: 706.40 | T1364: 11,250.00 | U1364: 562,500.00 | V1364: -561,793.60 | W1364: 상품 샘플링 (견본,무상증정) | X1364: -79,529.1 | Y1364: IN00408995 | AA1364: =LEFT(E1364,7) -> 2026-02 | AB1364: =IF(AND($AA1364>="2025-01",$AA1364<="2025-06"),"H1_2025",IF(AND($AA1364>="2026-01",$AA1364<="2026-06"),"H1_2026","")) -> H1_2026 | AC1364: =IFERROR(VALUE(SUBSTITUTE(S1364,",","")),0) -> 706.4 | AD1364: =IFERROR(VALUE(SUBSTITUTE(O1364,",","")),0) -> 50 | AE1364: =IFERROR(VALUE(SUBSTITUTE(V1364,",","")),0) -> -561793.6 | AF1364: =IF(ISNUMBER(SEARCH("FOC",W1364)),"FOC",IF(ISNUMBER(SEARCH("샘플",W1364)),"Sample","Paid")) -> Sample
A1365: 1363 | B1365: 06312 | C1365: KR | D1365: OPO | E1365: 2026-02-04 | F1365: erine | G1365: MOARS | I1365: Netherlands The | J1365: KR-OVERSEAS | K1365: RjAS01-CRMEU | L1365: [EU] 어드밴스드 PDRN 크림 60ml | M1365: 닥터 리쥬올 | N1365: USD | O1365: 50 | P1365: 0.01 | Q1365: 0.50 | R1365: 0.00 | S1365: 706.40 | T1365: 32,000.00 | U1365: 1,600,000.00 | V1365: -1,599,293.60 | W1365: 상품 샘플링 (견본,무상증정) | X1365: -226,400.6 | Y1365: IN00408995 | AA1365: =LEFT(E1365,7) -> 2026-02 | AB1365: =IF(AND($AA1365>="2025-01",$AA1365<="2025-06"),"H1_2025",IF(AND($AA1365>="2026-01",$AA1365<="2026-06"),"H1_2026","")) -> H1_2026 | AC1365: =IFERROR(VALUE(SUBSTITUTE(S1365,",","")),0) -> 706.4 | AD1365: =IFERROR(VALUE(SUBSTITUTE(O1365,",","")),0) -> 50 | AE1365: =IFERROR(VALUE(SUBSTITUTE(V1365,",","")),0) -> -1599293.6 | AF1365: =IF(ISNUMBER(SEARCH("FOC",W1365)),"FOC",IF(ISNUMBER(SEARCH("샘플",W1365)),"Sample","Paid")) -> Sample
A1366: 1364 | B1366: 06312 | C1366: KR | D1366: OPO | E1366: 2026-02-04 | F1366: erine | G1366: MOARS | I1366: Netherlands The | J1366: KR-OVERSEAS | K1366: ANC01-OCR | L1366: [리뉴얼] 어성초 포어 컨트롤 클렌징 오일 200ml | M1366: 아누아 | N1366: USD | O1366: 260 | P1366: 8.71 | Q1366: 2,264.60 | R1366: 0.00 | S1366: 3,260,344.62 | T1366: 0.00 | U1366: 0.00 | V1366: 3,260,344.62 | X1366: 100.0 | Y1366: IN00406040 | AA1366: =LEFT(E1366,7) -> 2026-02 | AB1366: =IF(AND($AA1366>="2025-01",$AA1366<="2025-06"),"H1_2025",IF(AND($AA1366>="2026-01",$AA1366<="2026-06"),"H1_2026","")) -> H1_2026 | AC1366: =IFERROR(VALUE(SUBSTITUTE(S1366,",","")),0) -> 3260344.6 | AD1366: =IFERROR(VALUE(SUBSTITUTE(O1366,",","")),0) -> 260 | AE1366: =IFERROR(VALUE(SUBSTITUTE(V1366,",","")),0) -> 3260344.6 | AF1366: =IF(ISNUMBER(SEARCH("FOC",W1366)),"FOC",IF(ISNUMBER(SEARCH("샘플",W1366)),"Sample","Paid")) -> Paid
A1367: 1365 | B1367: 06312 | C1367: KR | D1367: OPO | E1367: 2026-02-04 | F1367: erine | G1367: MOARS | I1367: Netherlands The | J1367: KR-OVERSEAS | K1367: ANC12-F | L1367: 8 히알루론산 하이드레이팅 젠틀 포밍 클렌저 150ml | M1367: 아누아 | N1367: USD | O1367: 100 | P1367: 6.13 | Q1367: 613.00 | R1367: 0.00 | S1367: 882,536.10 | T1367: 7,760.00 | U1367: 776,000.00 | V1367: 106,536.10 | X1367: 12.1 | Y1367: IN00406040 | AA1367: =LEFT(E1367,7) -> 2026-02 | AB1367: =IF(AND($AA1367>="2025-01",$AA1367<="2025-06"),"H1_2025",IF(AND($AA1367>="2026-01",$AA1367<="2026-06"),"H1_2026","")) -> H1_2026 | AC1367: =IFERROR(VALUE(SUBSTITUTE(S1367,",","")),0) -> 882536.1 | AD1367: =IFERROR(VALUE(SUBSTITUTE(O1367,",","")),0) -> 100 | AE1367: =IFERROR(VALUE(SUBSTITUTE(V1367,",","")),0) -> 106536.1 | AF1367: =IF(ISNUMBER(SEARCH("FOC",W1367)),"FOC",IF(ISNUMBER(SEARCH("샘플",W1367)),"Sample","Paid")) -> Paid
A1368: 1366 | B1368: 06312 | C1368: KR | D1368: OPO | E1368: 2026-02-04 | F1368: erine | G1368: MOARS | I1368: Netherlands The | J1368: KR-OVERSEAS | K1368: ANP06-MCOL | L1368: [4매입] 복숭아 70 나이아신 브라이트닝 콜라겐 마스크 | M1368: 아누아 | N1368: USD | O1368: 300 | P1368: 9.17 | Q1368: 2,751.00 | R1368: 0.00 | S1368: 3,960,614.70 | T1368: 11,630.00 | U1368: 3,489,000.00 | V1368: 471,614.70 | X1368: 11.9 | Y1368: IN00406040 | AA1368: =LEFT(E1368,7) -> 2026-02 | AB1368: =IF(AND($AA1368>="2025-01",$AA1368<="2025-06"),"H1_2025",IF(AND($AA1368>="2026-01",$AA1368<="2026-06"),"H1_2026","")) -> H1_2026 | AC1368: =IFERROR(VALUE(SUBSTITUTE(S1368,",","")),0) -> 3960614.7 | AD1368: =IFERROR(VALUE(SUBSTITUTE(O1368,",","")),0) -> 300 | AE1368: =IFERROR(VALUE(SUBSTITUTE(V1368,",","")),0) -> 471614.7 | AF1368: =IF(ISNUMBER(SEARCH("FOC",W1368)),"FOC",IF(ISNUMBER(SEARCH("샘플",W1368)),"Sample","Paid")) -> Paid
A1369: 1367 | B1369: 06312 | C1369: KR | D1369: OPO | E1369: 2026-02-04 | F1369: erine | G1369: MOARS | I1369: Netherlands The | J1369: KR-OVERSEAS | K1369: ANS10-SPDRN | L1369: PDRN 히알루론산 캡슐 100 세럼 30ml | M1369: 아누아 | N1369: USD | O1369: 900 | P1369: 12.19 | Q1369: 10,971.00 | R1369: 0.00 | S1369: 15,794,948.70 | T1369: 15,510.00 | U1369: 13,959,000.00 | V1369: 1,835,948.70 | X1369: 11.6 | Y1369: IN00406040 | AA1369: =LEFT(E1369,7) -> 2026-02 | AB1369: =IF(AND($AA1369>="2025-01",$AA1369<="2025-06"),"H1_2025",IF(AND($AA1369>="2026-01",$AA1369<="2026-06"),"H1_2026","")) -> H1_2026 | AC1369: =IFERROR(VALUE(SUBSTITUTE(S1369,",","")),0) -> 15794949 | AD1369: =IFERROR(VALUE(SUBSTITUTE(O1369,",","")),0) -> 900 | AE1369: =IFERROR(VALUE(SUBSTITUTE(V1369,",","")),0) -> 1835948.7 | AF1369: =IF(ISNUMBER(SEARCH("FOC",W1369)),"FOC",IF(ISNUMBER(SEARCH("샘플",W1369)),"Sample","Paid")) -> Paid
A1370: 1368 | B1370: 06312 | C1370: KR | D1370: OPO | E1370: 2026-01-30 | F1370: erine | G1370: MOARS | I1370: Netherlands The | J1370: KR-OVERSEAS | K1370: AbibP02-MHr | L1370: [1매입] 껌딱지 시트 마스크 어성초 스티커 (2023) | M1370: 아비브 | N1370: USD | O1370: 60 | P1370: 0.86 | Q1370: 51.60 | R1370: 0.00 | S1370: 74,489.76 | T1370: 546.97 | U1370: 32,818.18 | V1370: 41,671.58 | X1370: 55.9 | Y1370: IN00406800 | AA1370: =LEFT(E1370,7) -> 2026-01 | AB1370: =IF(AND($AA1370>="2025-01",$AA1370<="2025-06"),"H1_2025",IF(AND($AA1370>="2026-01",$AA1370<="2026-06"),"H1_2026","")) -> H1_2026 | AC1370: =IFERROR(VALUE(SUBSTITUTE(S1370,",","")),0) -> 74489.76 | AD1370: =IFERROR(VALUE(SUBSTITUTE(O1370,",","")),0) -> 60 | AE1370: =IFERROR(VALUE(SUBSTITUTE(V1370,",","")),0) -> 41671.58 | AF1370: =IF(ISNUMBER(SEARCH("FOC",W1370)),"FOC",IF(ISNUMBER(SEARCH("샘플",W1370)),"Sample","Paid")) -> Paid
A1371: 1369 | B1371: 06312 | C1371: KR | D1371: OPO | E1371: 2026-01-30 | F1371: erine | G1371: MOARS | I1371: Netherlands The | J1371: KR-OVERSEAS | K1371: AbibP02-MHyrR | L1371: [1매입] 껌딱지 시트 마스크 수분초 히알루론 스티커 (2024) | M1371: 아비브 | N1371: USD | O1371: 80 | P1371: 0.86 | Q1371: 68.80 | R1371: 0.00 | S1371: 99,319.68 | T1371: 863.64 | U1371: 69,090.90 | V1371: 30,228.78 | X1371: 30.4 | Y1371: IN00406800 | AA1371: =LEFT(E1371,7) -> 2026-01 | AB1371: =IF(AND($AA1371>="2025-01",$AA1371<="2025-06"),"H1_2025",IF(AND($AA1371>="2026-01",$AA1371<="2026-06"),"H1_2026","")) -> H1_2026 | AC1371: =IFERROR(VALUE(SUBSTITUTE(S1371,",","")),0) -> 99319.68 | AD1371: =IFERROR(VALUE(SUBSTITUTE(O1371,",","")),0) -> 80 | AE1371: =IFERROR(VALUE(SUBSTITUTE(V1371,",","")),0) -> 30228.78 | AF1371: =IF(ISNUMBER(SEARCH("FOC",W1371)),"FOC",IF(ISNUMBER(SEARCH("샘플",W1371)),"Sample","Paid")) -> Paid
A1372: 1370 | B1372: 06312 | C1372: KR | D1372: OPO | E1372: 2026-01-30 | F1372: erine | G1372: MOARS | I1372: Netherlands The | J1372: KR-OVERSEAS | K1372: AbibP02-MMr | L1372: [1매입] 껌딱지 시트 마스크 콜라겐 밀크 스티커 (2023) | M1372: 아비브 | N1372: USD | O1372: 270 | P1372: 0.86 | Q1372: 232.20 | R1372: 0.00 | S1372: 335,203.92 | T1372: 863.64 | U1372: 233,181.80 | V1372: 102,022.12 | X1372: 30.4 | Y1372: IN00406800 | AA1372: =LEFT(E1372,7) -> 2026-01 | AB1372: =IF(AND($AA1372>="2025-01",$AA1372<="2025-06"),"H1_2025",IF(AND($AA1372>="2026-01",$AA1372<="2026-06"),"H1_2026","")) -> H1_2026 | AC1372: =IFERROR(VALUE(SUBSTITUTE(S1372,",","")),0) -> 335203.92 | AD1372: =IFERROR(VALUE(SUBSTITUTE(O1372,",","")),0) -> 270 | AE1372: =IFERROR(VALUE(SUBSTITUTE(V1372,",","")),0) -> 102022.12 | AF1372: =IF(ISNUMBER(SEARCH("FOC",W1372)),"FOC",IF(ISNUMBER(SEARCH("샘플",W1372)),"Sample","Paid")) -> Paid
A1373: 1371 | B1373: 06312 | C1373: KR | D1373: OPO | E1373: 2026-01-30 | F1373: erine | G1373: MOARS | I1373: Netherlands The | J1373: KR-OVERSEAS | K1373: AbibP02-Mvita | L1373: [1매입] 껌딱지 시트 마스크 비타 스티커 (2023) | M1373: 아비브 | N1373: USD | O1373: 60 | P1373: 0.86 | Q1373: 51.60 | R1373: 0.00 | S1373: 74,489.76 | T1373: 863.64 | U1373: 51,818.18 | V1373: 22,671.58 | X1373: 30.4 | Y1373: IN00406800 | AA1373: =LEFT(E1373,7) -> 2026-01 | AB1373: =IF(AND($AA1373>="2025-01",$AA1373<="2025-06"),"H1_2025",IF(AND($AA1373>="2026-01",$AA1373<="2026-06"),"H1_2026","")) -> H1_2026 | AC1373: =IFERROR(VALUE(SUBSTITUTE(S1373,",","")),0) -> 74489.76 | AD1373: =IFERROR(VALUE(SUBSTITUTE(O1373,",","")),0) -> 60 | AE1373: =IFERROR(VALUE(SUBSTITUTE(V1373,",","")),0) -> 22671.58 | AF1373: =IF(ISNUMBER(SEARCH("FOC",W1373)),"FOC",IF(ISNUMBER(SEARCH("샘플",W1373)),"Sample","Paid")) -> Paid
A1374: 1372 | B1374: 06312 | C1374: KR | D1374: OPO | E1374: 2026-01-30 | F1374: erine | G1374: MOARS | I1374: Netherlands The | J1374: KR-OVERSEAS | K1374: AbibP09-Mlf | L1374: [1매입] 약산성 pH 시트 마스크 어성초 핏 | M1374: 아비브 | N1374: USD | O1374: 50 | P1374: 0.89 | Q1374: 44.50 | R1374: 0.00 | S1374: 64,240.20 | T1374: 915.45 | U1374: 45,772.73 | V1374: 18,467.47 | X1374: 28.7 | Y1374: IN00406800 | AA1374: =LEFT(E1374,7) -> 2026-01 | AB1374: =IF(AND($AA1374>="2025-01",$AA1374<="2025-06"),"H1_2025",IF(AND($AA1374>="2026-01",$AA1374<="2026-06"),"H1_2026","")) -> H1_2026 | AC1374: =IFERROR(VALUE(SUBSTITUTE(S1374,",","")),0) -> 64240.2 | AD1374: =IFERROR(VALUE(SUBSTITUTE(O1374,",","")),0) -> 50 | AE1374: =IFERROR(VALUE(SUBSTITUTE(V1374,",","")),0) -> 18467.47 | AF1374: =IF(ISNUMBER(SEARCH("FOC",W1374)),"FOC",IF(ISNUMBER(SEARCH("샘플",W1374)),"Sample","Paid")) -> Paid
A1375: 1373 | B1375: 06312 | C1375: KR | D1375: OPO | E1375: 2026-01-30 | F1375: erine | G1375: MOARS | I1375: Netherlands The | J1375: KR-OVERSEAS | K1375: AbibP11-M4ea | L1375: [4매입] 콜라겐 겔 마스크_어성초 젤리 | M1375: 아비브 | N1375: USD | O1375: 90 | P1375: 4.85 | Q1375: 436.50 | R1375: 0.00 | S1375: 630,131.40 | T1375: 5,301.82 | U1375: 477,163.63 | V1375: 152,967.77 | X1375: 24.3 | Y1375: IN00406800 | AA1375: =LEFT(E1375,7) -> 2026-01 | AB1375: =IF(AND($AA1375>="2025-01",$AA1375<="2025-06"),"H1_2025",IF(AND($AA1375>="2026-01",$AA1375<="2026-06"),"H1_2026","")) -> H1_2026 | AC1375: =IFERROR(VALUE(SUBSTITUTE(S1375,",","")),0) -> 630131.4 | AD1375: =IFERROR(VALUE(SUBSTITUTE(O1375,",","")),0) -> 90 | AE1375: =IFERROR(VALUE(SUBSTITUTE(V1375,",","")),0) -> 152967.77 | AF1375: =IF(ISNUMBER(SEARCH("FOC",W1375)),"FOC",IF(ISNUMBER(SEARCH("샘플",W1375)),"Sample","Paid")) -> Paid
A1376: 1374 | B1376: 06312 | C1376: KR | D1376: OPO | E1376: 2026-01-30 | F1376: erine | G1376: MOARS | I1376: Netherlands The | J1376: KR-OVERSEAS | K1376: AbibP20-Meye | L1376: 콜라겐 아이패치_부활초 젤리 60매 | M1376: 아비브 | N1376: USD | O1376: 60 | P1376: 6.69 | Q1376: 401.40 | R1376: 0.00 | S1376: 579,461.04 | T1376: 7,567.00 | U1376: 454,020.00 | V1376: 125,441.04 | X1376: 21.6 | Y1376: IN00406800 | AA1376: =LEFT(E1376,7) -> 2026-01 | AB1376: =IF(AND($AA1376>="2025-01",$AA1376<="2025-06"),"H1_2025",IF(AND($AA1376>="2026-01",$AA1376<="2026-06"),"H1_2026","")) -> H1_2026 | AC1376: =IFERROR(VALUE(SUBSTITUTE(S1376,",","")),0) -> 579461.04 | AD1376: =IFERROR(VALUE(SUBSTITUTE(O1376,",","")),0) -> 60 | AE1376: =IFERROR(VALUE(SUBSTITUTE(V1376,",","")),0) -> 125441.04 | AF1376: =IF(ISNUMBER(SEARCH("FOC",W1376)),"FOC",IF(ISNUMBER(SEARCH("샘플",W1376)),"Sample","Paid")) -> Paid
A1377: 1375 | B1377: 06312 | C1377: KR | D1377: OPO | E1377: 2026-01-30 | F1377: erine | G1377: MOARS | I1377: Netherlands The | J1377: KR-OVERSEAS | K1377: AbibS11-C | L1377: 어성초 크림 카밍 튜브 75ml | M1377: 아비브 | N1377: USD | O1377: 90 | P1377: 6.79 | Q1377: 611.10 | R1377: 0.00 | S1377: 882,183.96 | T1377: 6,900.00 | U1377: 621,000.00 | V1377: 261,183.96 | X1377: 29.6 | Y1377: IN00406800 | AA1377: =LEFT(E1377,7) -> 2026-01 | AB1377: =IF(AND($AA1377>="2025-01",$AA1377<="2025-06"),"H1_2025",IF(AND($AA1377>="2026-01",$AA1377<="2026-06"),"H1_2026","")) -> H1_2026 | AC1377: =IFERROR(VALUE(SUBSTITUTE(S1377,",","")),0) -> 882183.96 | AD1377: =IFERROR(VALUE(SUBSTITUTE(O1377,",","")),0) -> 90 | AE1377: =IFERROR(VALUE(SUBSTITUTE(V1377,",","")),0) -> 261183.96 | AF1377: =IF(ISNUMBER(SEARCH("FOC",W1377)),"FOC",IF(ISNUMBER(SEARCH("샘플",W1377)),"Sample","Paid")) -> Paid
... A1578: 1576 | B1578: 06312 | C1578: KR | D1578: OPO | E1578: 2026-01-29 | F1578: erine | G1578: MOARS | I1578: Netherlands The | J1578: KR-OVERSEAS | K1578: MMS01-SB80 | L1578: 병풀 추출물 세럼 80ml | M1578: 마리엔메이 | N1578: USD | O1578: 100 | P1578: 7.96 | Q1578: 796.00 | R1578: 0.00 | S1578: 1,127,772.80 | T1578: 7,650.00 | U1578: 765,000.00 | V1578: 362,772.80 | X1578: 32.2 | Y1578: IN00402593 | AA1578: =LEFT(E1578,7) -> 2026-01 | AB1578: =IF(AND($AA1578>="2025-01",$AA1578<="2025-06"),"H1_2025",IF(AND($AA1578>="2026-01",$AA1578<="2026-06"),"H1_2026","")) -> H1_2026 | AC1578: =IFERROR(VALUE(SUBSTITUTE(S1578,",","")),0) -> 1127772.8 | AD1578: =IFERROR(VALUE(SUBSTITUTE(O1578,",","")),0) -> 100 | AE1578: =IFERROR(VALUE(SUBSTITUTE(V1578,",","")),0) -> 362772.8 | AF1578: =IF(ISNUMBER(SEARCH("FOC",W1578)),"FOC",IF(ISNUMBER(SEARCH("샘플",W1578)),"Sample","Paid")) -> Paid
A1579: 1577 | B1579: 06312 | C1579: KR | D1579: OPO | E1579: 2026-01-29 | F1579: erine | G1579: MOARS | I1579: Netherlands The | J1579: KR-OVERSEAS | K1579: MMS06-IR | L1579: (리뉴얼) 트라넥사믹산 + 글루타치온 아이크림 30g | M1579: 마리엔메이 | N1579: USD | O1579: 244 | P1579: 0.00 | Q1579: 0.00 | R1579: 0.00 | S1579: 0.00 | T1579: 4,980.00 | U1579: 1,215,120.00 | V1579: -1,215,120.00 | W1579: 상품 샘플링 (견본,무상증정) | X1579: 0.0 | Y1579: IN00402593 | AA1579: =LEFT(E1579,7) -> 2026-01 | AB1579: =IF(AND($AA1579>="2025-01",$AA1579<="2025-06"),"H1_2025",IF(AND($AA1579>="2026-01",$AA1579<="2026-06"),"H1_2026","")) -> H1_2026 | AC1579: =IFERROR(VALUE(SUBSTITUTE(S1579,",","")),0) -> 0 | AD1579: =IFERROR(VALUE(SUBSTITUTE(O1579,",","")),0) -> 244 | AE1579: =IFERROR(VALUE(SUBSTITUTE(V1579,",","")),0) -> -1215120 | AF1579: =IF(ISNUMBER(SEARCH("FOC",W1579)),"FOC",IF(ISNUMBER(SEARCH("샘플",W1579)),"Sample","Paid")) -> Sample
A1580: 1578 | B1580: 06312 | C1580: KR | D1580: OPO | E1580: 2026-01-29 | F1580: erine | G1580: MOARS | I1580: Netherlands The | J1580: KR-OVERSEAS | K1580: MMS14-ISETR | L1580: (리뉴얼) 트라넥사믹산+글루타티온 아이크림 기획세트 (30g+12g x2) | M1580: 마리엔메이 | N1580: USD | O1580: 300 | P1580: 6.22 | Q1580: 1,866.00 | R1580: 0.00 | S1580: 2,643,748.80 | T1580: 5,500.00 | U1580: 1,650,000.00 | V1580: 993,748.80 | X1580: 37.6 | Y1580: IN00402593 | AA1580: =LEFT(E1580,7) -> 2026-01 | AB1580: =IF(AND($AA1580>="2025-01",$AA1580<="2025-06"),"H1_2025",IF(AND($AA1580>="2026-01",$AA1580<="2026-06"),"H1_2026","")) -> H1_2026 | AC1580: =IFERROR(VALUE(SUBSTITUTE(S1580,",","")),0) -> 2643748.8 | AD1580: =IFERROR(VALUE(SUBSTITUTE(O1580,",","")),0) -> 300 | AE1580: =IFERROR(VALUE(SUBSTITUTE(V1580,",","")),0) -> 993748.8 | AF1580: =IF(ISNUMBER(SEARCH("FOC",W1580)),"FOC",IF(ISNUMBER(SEARCH("샘플",W1580)),"Sample","Paid")) -> Paid
A1581: 1579 | B1581: 06312 | C1581: KR | D1581: OPO | E1581: 2026-01-29 | F1581: erine | G1581: MOARS | I1581: Netherlands The | J1581: KR-OVERSEAS | K1581: TKBCM11-LRC | L1581: [체코용]파우더 크림 립밤 031 로즈 번 | M1581: 토코보 | N1581: USD | O1581: 60 | P1581: 0.00 | Q1581: 0.00 | R1581: 0.00 | S1581: 0.00 | T1581: 3,280.00 | U1581: 196,800.00 | V1581: -196,800.00 | W1581: 상품 샘플링 (견본,무상증정) | X1581: 0.0 | Y1581: IN00402593 | AA1581: =LEFT(E1581,7) -> 2026-01 | AB1581: =IF(AND($AA1581>="2025-01",$AA1581<="2025-06"),"H1_2025",IF(AND($AA1581>="2026-01",$AA1581<="2026-06"),"H1_2026","")) -> H1_2026 | AC1581: =IFERROR(VALUE(SUBSTITUTE(S1581,",","")),0) -> 0 | AD1581: =IFERROR(VALUE(SUBSTITUTE(O1581,",","")),0) -> 60 | AE1581: =IFERROR(VALUE(SUBSTITUTE(V1581,",","")),0) -> -196800 | AF1581: =IF(ISNUMBER(SEARCH("FOC",W1581)),"FOC",IF(ISNUMBER(SEARCH("샘플",W1581)),"Sample","Paid")) -> Sample
A1582: 1580 | B1582: 06312 | C1582: KR | D1582: OPO | E1582: 2025-12-22 | F1582: erine | G1582: MOARS | I1582: Netherlands The | J1582: KR-OVERSEAS | K1582: CMXBS02-Pr | L1582: 원스텝 바디 브라이트닝 패드 60EA | M1582: 셀리맥스 | N1582: USD | O1582: 160 | P1582: 5.42 | Q1582: 867.20 | R1582: 0.00 | S1582: 1,249,114.88 | T1582: 5,836.00 | U1582: 933,760.00 | V1582: 315,354.88 | X1582: 25.2 | Y1582: IN00396777 | AA1582: =LEFT(E1582,7) -> 2025-12 | AB1582: =IF(AND($AA1582>="2025-01",$AA1582<="2025-06"),"H1_2025",IF(AND($AA1582>="2026-01",$AA1582<="2026-06"),"H1_2026","")) | AC1582: =IFERROR(VALUE(SUBSTITUTE(S1582,",","")),0) -> 1249114.9 | AD1582: =IFERROR(VALUE(SUBSTITUTE(O1582,",","")),0) -> 160 | AE1582: =IFERROR(VALUE(SUBSTITUTE(V1582,",","")),0) -> 315354.88 | AF1582: =IF(ISNUMBER(SEARCH("FOC",W1582)),"FOC",IF(ISNUMBER(SEARCH("샘플",W1582)),"Sample","Paid")) -> Paid
...

Sheet H1 Analysis
A1: MOARS — H1 Sales Review & Comparison: 2025 vs 2026
A2: Client: MOARS (ships to Netherlands) · Currency: KRW (converted amount / 환산금액) · Period: Jan–Jun · Purpose: H1 retrospective & H2 insight · Source: {worksheet}
A4: KEY METRICS
A5: Metric | B5: H1 2025 | C5: H1 2026 | D5: Δ | E5: YoY %
A6: Total Revenue (KRW) | B6: =SUMIFS('{worksheet}'!$AC$3:$AC$4127,'{worksheet}'!$AB$3:$AB$4127,"H1_2025") -> 4.5228118e+09 | C6: =SUMIFS('{worksheet}'!$AC$3:$AC$4127,'{worksheet}'!$AB$3:$AB$4127,"H1_2026") -> 8.1526898e+09 | D6: =C6-B6 -> 3.629878e+09 | E6: =IF(B6=0,"",C6/B6-1) -> 0.80257109
A7: Gross Profit (KRW) | B7: =SUMIFS('{worksheet}'!$AE$3:$AE$4127,'{worksheet}'!$AB$3:$AB$4127,"H1_2025") -> 9.0410372e+08 | C7: =SUMIFS('{worksheet}'!$AE$3:$AE$4127,'{worksheet}'!$AB$3:$AB$4127,"H1_2026") -> 1.8934963e+09 | D7: =C7-B7 -> 9.8939253e+08 | E7: =IF(B7=0,"",C7/B7-1) -> 1.0943352
A8: Gross Margin % | B8: =IF(B6=0,"",B7/B6) -> 0.19989859 | C8: =IF(C6=0,"",C7/C6) -> 0.23225418 | D8: =IF(OR(B8="",C8=""),"",C8-B8) -> 0.032355582
A9: Units Sold | B9: =SUMIFS('{worksheet}'!$AD$3:$AD$4127,'{worksheet}'!$AB$3:$AB$4127,"H1_2025") -> 939458 | C9: =SUMIFS('{worksheet}'!$AD$3:$AD$4127,'{worksheet}'!$AB$3:$AB$4127,"H1_2026") -> 807407 | D9: =C9-B9 -> -132051 | E9: =IF(B9=0,"",C9/B9-1) -> -0.14056083
A10: Transactions (line items) | B10: =COUNTIFS('{worksheet}'!$AB$3:$AB$4127,"H1_2025") -> 949 | C10: =COUNTIFS('{worksheet}'!$AB$3:$AB$4127,"H1_2026") -> 1566 | D10: =C10-B10 -> 617 | E10: =IF(B10=0,"",C10/B10-1) -> 0.65015806
A11: Active Brands (rev > 0) | B11: =COUNTIF($D$26:$D$117,">0") -> 59 | C11: =COUNTIF($E$26:$E$117,">0") -> 63 | D11: =C11-B11 -> 4
A12: Free Units (Sample + FOC) | B12: =SUMIFS('{worksheet}'!$AD$3:$AD$4127,'{worksheet}'!$AB$3:$AB$4127,"H1_2025",'{worksheet}'!$AF$3:$AF$4127,"Sample")+SUMIFS('{worksheet}'!$AD$3:$AD$4127,'{worksheet}'!$AB$3:$AB$4127,"H1_2025",'{worksheet}'!$AF$3:$AF$4127,"FOC") -> 36542 | C12: =SUMIFS('{worksheet}'!$AD$3:$AD$4127,'{worksheet}'!$AB$3:$AB$4127,"H1_2026",'{worksheet}'!$AF$3:$AF$4127,"Sample")+SUMIFS('{worksheet}'!$AD$3:$AD$4127,'{worksheet}'!$AB$3:$AB$4127,"H1_2026",'{worksheet}'!$AF$3:$AF$4127,"FOC") -> 7223 | D12: =C12-B12 -> -29319 | E12: =IF(B12=0,"",C12/B12-1) -> -0.80233704
A14: MONTHLY REVENUE TREND (KRW)
A15: Month | B15: 2025 | C15: 2026 | D15: YoY %
A16: Jan | B16: =SUMIFS('{worksheet}'!$AC$3:$AC$4127,'{worksheet}'!$AA$3:$AA$4127,"2025-"&TEXT(ROW()-15,"00")) -> 94130266 | C16: =SUMIFS('{worksheet}'!$AC$3:$AC$4127,'{worksheet}'!$AA$3:$AA$4127,"2026-"&TEXT(ROW()-15,"00")) -> 4.5555454e+08 | D16: =IF(B16=0,"",C16/B16-1) -> 3.8396181
A17: Feb | B17: =SUMIFS('{worksheet}'!$AC$3:$AC$4127,'{worksheet}'!$AA$3:$AA$4127,"2025-"&TEXT(ROW()-15,"00")) -> 5.6477425e+08 | C17: =SUMIFS('{worksheet}'!$AC$3:$AC$4127,'{worksheet}'!$AA$3:$AA$4127,"2026-"&TEXT(ROW()-15,"00")) -> 1.1587206e+09 | D17: =IF(B17=0,"",C17/B17-1) -> 1.0516527
A18: Mar | B18: =SUMIFS('{worksheet}'!$AC$3:$AC$4127,'{worksheet}'!$AA$3:$AA$4127,"2025-"&TEXT(ROW()-15,"00")) -> 1.058785e+09 | C18: =SUMIFS('{worksheet}'!$AC$3:$AC$4127,'{worksheet}'!$AA$3:$AA$4127,"2026-"&TEXT(ROW()-15,"00")) -> 1.9159751e+09 | D18: =IF(B18=0,"",C18/B18-1) -> 0.80959782
A19: Apr | B19: =SUMIFS('{worksheet}'!$AC$3:$AC$4127,'{worksheet}'!$AA$3:$AA$4127,"2025-"&TEXT(ROW()-15,"00")) -> 1.0903516e+09 | C19: =SUMIFS('{worksheet}'!$AC$3:$AC$4127,'{worksheet}'!$AA$3:$AA$4127,"2026-"&TEXT(ROW()-15,"00")) -> 8.8905312e+08 | D19: =IF(B19=0,"",C19/B19-1) -> -0.18461793
A20: May | B20: =SUMIFS('{worksheet}'!$AC$3:$AC$4127,'{worksheet}'!$AA$3:$AA$4127,"2025-"&TEXT(ROW()-15,"00")) -> 8.8225913e+08 | C20: =SUMIFS('{worksheet}'!$AC$3:$AC$4127,'{worksheet}'!$AA$3:$AA$4127,"2026-"&TEXT(ROW()-15,"00")) -> 1.284503e+09 | D20: =IF(B20=0,"",C20/B20-1) -> 0.45592487
A21: Jun | B21: =SUMIFS('{worksheet}'!$AC$3:$AC$4127,'{worksheet}'!$AA$3:$AA$4127,"2025-"&TEXT(ROW()-15,"00")) -> 8.3251153e+08 | C21: =SUMIFS('{worksheet}'!$AC$3:$AC$4127,'{worksheet}'!$AA$3:$AA$4127,"2026-"&TEXT(ROW()-15,"00")) -> 2.4488834e+09 | D21: =IF(B21=0,"",C21/B21-1) -> 1.941561
A22: H1 Total | B22: =SUM(B16:B21) -> 4.5228118e+09 | C22: =SUM(C16:C21) -> 8.1526898e+09 | D22: =IF(B22=0,"",C22/B22-1) -> 0.80257109
A24: BRAND COMPARISON — H1 2025 vs H1 2026 (Revenue in KRW, sorted by H1'26 revenue)
A25: # | B25: Brand (EN) | C25: Brand (source) | D25: Rev H1'25 | E25: Rev H1'26 | F25: Δ Rev | G25: YoY % | H25: Units'25 | I25: Units'26 | J25: Profit'26 | K25: Margin'26 | L25: Free units'26 | M25: Status
A26: 1 | B26: Beauty of Joseon | C26: 조선미녀 | D26: =SUMIFS('{worksheet}'!$AC$3:$AC$4127,'{worksheet}'!$AB$3:$AB$4127,"H1_2025",'{worksheet}'!$M$3:$M$4127,$C26) -> 2.1048138e+09 | E26: =SUMIFS('{worksheet}'!$AC$3:$AC$4127,'{worksheet}'!$AB$3:$AB$4127,"H1_2026",'{worksheet}'!$M$3:$M$4127,$C26) -> 2.2701934e+09 | F26: =E26-D26 -> 1.6537959e+08 | G26: =IF(D26=0,"",E26/D26-1) -> 0.078572079 | H26: =SUMIFS('{worksheet}'!$AD$3:$AD$4127,'{worksheet}'!$AB$3:$AB$4127,"H1_2025",'{worksheet}'!$M$3:$M$4127,$C26) -> 225916 | I26: =SUMIFS('{worksheet}'!$AD$3:$AD$4127,'{worksheet}'!$AB$3:$AB$4127,"H1_2026",'{worksheet}'!$M$3:$M$4127,$C26) -> 233800 | J26: =SUMIFS('{worksheet}'!$AE$3:$AE$4127,'{worksheet}'!$AB$3:$AB$4127,"H1_2026",'{worksheet}'!$M$3:$M$4127,$C26) -> 4.8589813e+08 | K26: =IF(E26=0,"",J26/E26) -> 0.21403381 | L26: =SUMIFS('{worksheet}'!$AD$3:$AD$4127,'{worksheet}'!$AB$3:$AB$4127,"H1_2026",'{worksheet}'!$M$3:$M$4127,$C26,'{worksheet}'!$AF$3:$AF$4127,"Sample")+SUMIFS('{worksheet}'!$AD$3:$AD$4127,'{worksheet}'!$AB$3:$AB$4127,"H1_2026",'{worksheet}'!$M$3:$M$4127,$C26,'{worksheet}'!$AF$3:$AF$4127,"FOC") -> 0 | M26: =IF(AND(D26=0,E26>0),"New in H1'26",IF(AND(D26>0,E26=0),"Exited",IF(G26="","",IF(G26>=0.2,"Growth",IF(G26<=-0.2,"Decline","Stable"))))) -> Stable
A27: 2 | B27: medicube | C27: 메디큐브 | D27: =SUMIFS('{worksheet}'!$AC$3:$AC$4127,'{worksheet}'!$AB$3:$AB$4127,"H1_2025",'{worksheet}'!$M$3:$M$4127,$C27) -> 3.9262294e+08 | E27: =SUMIFS('{worksheet}'!$AC$3:$AC$4127,'{worksheet}'!$AB$3:$AB$4127,"H1_2026",'{worksheet}'!$M$3:$M$4127,$C27) -> 1.9810588e+09 | F27: =E27-D27 -> 1.5884358e+09 | G27: =IF(D27=0,"",E27/D27-1) -> 4.0457031 | H27: =SUMIFS('{worksheet}'!$AD$3:$AD$4127,'{worksheet}'!$AB$3:$AB$4127,"H1_2025",'{worksheet}'!$M$3:$M$4127,$C27) -> 25040 | I27: =SUMIFS('{worksheet}'!$AD$3:$AD$4127,'{worksheet}'!$AB$3:$AB$4127,"H1_2026",'{worksheet}'!$M$3:$M$4127,$C27) -> 136613 | J27: =SUMIFS('{worksheet}'!$AE$3:$AE$4127,'{worksheet}'!$AB$3:$AB$4127,"H1_2026",'{worksheet}'!$M$3:$M$4127,$C27) -> 4.2827852e+08 | K27: =IF(E27=0,"",J27/E27) -> 0.21618668 | L27: =SUMIFS('{worksheet}'!$AD$3:$AD$4127,'{worksheet}'!$AB$3:$AB$4127,"H1_2026",'{worksheet}'!$M$3:$M$4127,$C27,'{worksheet}'!$AF$3:$AF$4127,"Sample")+SUMIFS('{worksheet}'!$AD$3:$AD$4127,'{worksheet}'!$AB$3:$AB$4127,"H1_2026",'{worksheet}'!$M$3:$M$4127,$C27,'{worksheet}'!$AF$3:$AF$4127,"FOC") -> 0 | M27: =IF(AND(D27=0,E27>0),"New in H1'26",IF(AND(D27>0,E27=0),"Exited",IF(G27="","",IF(G27>=0.2,"Growth",IF(G27<=-0.2,"Decline","Stable"))))) -> Growth
A28: 3 | B28: Anua | C28: 아누아 | D28: =SUMIFS('{worksheet}'!$AC$3:$AC$4127,'{worksheet}'!$AB$3:$AB$4127,"H1_2025",'{worksheet}'!$M$3:$M$4127,$C28) -> 20961 | E28: =SUMIFS('{worksheet}'!$AC$3:$AC$4127,'{worksheet}'!$AB$3:$AB$4127,"H1_2026",'{worksheet}'!$M$3:$M$4127,$C28) -> 1.4155911e+09 | F28: =E28-D28 -> 1.4155701e+09 | G28: =IF(D28=0,"",E28/D28-1) -> 67533.521 | H28: =SUMIFS('{worksheet}'!$AD$3:$AD$4127,'{worksheet}'!$AB$3:$AB$4127,"H1_2025",'{worksheet}'!$M$3:$M$4127,$C28) -> 1513 | I28: =SUMIFS('{worksheet}'!$AD$3:$AD$4127,'{worksheet}'!$AB$3:$AB$4127,"H1_2026",'{worksheet}'!$M$3:$M$4127,$C28) -> 121374 | J28: =SUMIFS('{worksheet}'!$AE$3:$AE$4127,'{worksheet}'!$AB$3:$AB$4127,"H1_2026",'{worksheet}'!$M$3:$M$4127,$C28) -> 2.8123517e+08 | K28: =IF(E28=0,"",J28/E28) -> 0.19866978 | L28: =SUMIFS('{worksheet}'!$AD$3:$AD$4127,'{worksheet}'!$AB$3:$AB$4127,"H1_2026",'{worksheet}'!$M$3:$M$4127,$C28,'{worksheet}'!$AF$3:$AF$4127,"Sample")+SUMIFS('{worksheet}'!$AD$3:$AD$4127,'{worksheet}'!$AB$3:$AB$4127,"H1_2026",'{worksheet}'!$M$3:$M$4127,$C28,'{worksheet}'!$AF$3:$AF$4127,"FOC") -> 0 | M28: =IF(AND(D28=0,E28>0),"New in H1'26",IF(AND(D28>0,E28=0),"Exited",IF(G28="","",IF(G28>=0.2,"Growth",IF(G28<=-0.2,"Decline","Stable"))))) -> Growth
A29: 4 | B29: COSRX | C29: 코스알엑스 | D29: =SUMIFS('{worksheet}'!$AC$3:$AC$4127,'{worksheet}'!$AB$3:$AB$4127,"H1_2025",'{worksheet}'!$M$3:$M$4127,$C29) -> 97689804 | E29: =SUMIFS('{worksheet}'!$AC$3:$AC$4127,'{worksheet}'!$AB$3:$AB$4127,"H1_2026",'{worksheet}'!$M$3:$M$4127,$C29) -> 4.3602826e+08 | F29: =E29-D29 -> 3.3833846e+08 | G29: =IF(D29=0,"",E29/D29-1) -> 3.4633958 | H29: =SUMIFS('{worksheet}'!$AD$3:$AD$4127,'{worksheet}'!$AB$3:$AB$4127,"H1_2025",'{worksheet}'!$M$3:$M$4127,$C29) -> 14537 | I29: =SUMIFS('{worksheet}'!$AD$3:$AD$4127,'{worksheet}'!$AB$3:$AB$4127,"H1_2026",'{worksheet}'!$M$3:$M$4127,$C29) -> 50859 | J29: =SUMIFS('{worksheet}'!$AE$3:$AE$4127,'{worksheet}'!$AB$3:$AB$4127,"H1_2026",'{worksheet}'!$M$3:$M$4127,$C29) -> 1.1373443e+08 | K29: =IF(E29=0,"",J29/E29) -> 0.26084187 | L29: =SUMIFS('{worksheet}'!$AD$3:$AD$4127,'{worksheet}'!$AB$3:$AB$4127,"H1_2026",'{worksheet}'!$M$3:$M$4127,$C29,'{worksheet}'!$AF$3:$AF$4127,"Sample")+SUMIFS('{worksheet}'!$AD$3:$AD$4127,'{worksheet}'!$AB$3:$AB$4127,"H1_2026",'{worksheet}'!$M$3:$M$4127,$C29,'{worksheet}'!$AF$3:$AF$4127,"FOC") -> 0 | M29: =IF(AND(D29=0,E29>0),"New in H1'26",IF(AND(D29>0,E29=0),"Exited",IF(G29="","",IF(G29>=0.2,"Growth",IF(G29<=-0.2,"Decline","Stable"))))) -> Growth
A30: 5 | B30: Round Lab | C30: 라운드랩 | D30: =SUMIFS('{worksheet}'!$AC$3:$AC$4127,'{worksheet}'!$AB$3:$AB$4127,"H1_2025",'{worksheet}'!$M$3:$M$4127,$C30) -> 48847212 | E30: =SUMIFS('{worksheet}'!$AC$3:$AC$4127,'{worksheet}'!$AB$3:$AB$4127,"H1_2026",'{worksheet}'!$M$3:$M$4127,$C30) -> 3.1603714e+08 | F30: =E30-D30 -> 2.6718993e+08 | G30: =IF(D30=0,"",E30/D30-1) -> 5.4699114 | H30: =SUMIFS('{worksheet}'!$AD$3:$AD$4127,'{worksheet}'!$AB$3:$AB$4127,"H1_2025",'{worksheet}'!$M$3:$M$4127,$C30) -> 15098 | I30: =SUMIFS('{worksheet}'!$AD$3:$AD$4127,'{worksheet}'!$AB$3:$AB$4127,"H1_2026",'{worksheet}'!$M$3:$M$4127,$C30) -> 42384 | J30: =SUMIFS('{worksheet}'!$AE$3:$AE$4127,'{worksheet}'!$AB$3:$AB$4127,"H1_2026",'{worksheet}'!$M$3:$M$4127,$C30) -> 76256088 | K30: =IF(E30=0,"",J30/E30) -> 0.24128838 | L30: =SUMIFS('{worksheet}'!$AD$3:$AD$4127,'{worksheet}'!$AB$3:$AB$4127,"H1_2026",'{worksheet}'!$M$3:$M$4127,$C30,'{worksheet}'!$AF$3:$AF$4127,"Sample")+SUMIFS('{worksheet}'!$AD$3:$AD$4127,'{worksheet}'!$AB$3:$AB$4127,"H1_2026",'{worksheet}'!$M$3:$M$4127,$C30,'{worksheet}'!$AF$3:$AF$4127,"FOC") -> 0 | M30: =IF(AND(D30=0,E30>0),"New in H1'26",IF(AND(D30>0,E30=0),"Exited",IF(G30="","",IF(G30>=0.2,"Growth",IF(G30<=-0.2,"Decline","Stable"))))) -> Growth
A31: 6 | B31: Celimax | C31: 셀리맥스 | D31: =SUMIFS('{worksheet}'!$AC$3:$AC$4127,'{worksheet}'!$AB$3:$AB$4127,"H1_2025",'{worksheet}'!$M$3:$M$4127,$C31) -> 74354178 | E31: =SUMIFS('{worksheet}'!$AC$3:$AC$4127,'{worksheet}'!$AB$3:$AB$4127,"H1_2026",'{worksheet}'!$M$3:$M$4127,$C31) -> 2.8216878e+08 | F31: =E31-D31 -> 2.0781461e+08 | G31: =IF(D31=0,"",E31/D31-1) -> 2.7949284 | H31: =SUMIFS('{worksheet}'!$AD$3:$AD$4127,'{worksheet}'!$AB$3:$AB$4127,"H1_2025",'{worksheet}'!$M$3:$M$4127,$C31) -> 8842 | I31: =SUMIFS('{worksheet}'!$AD$3:$AD$4127,'{worksheet}'!$AB$3:$AB$4127,"H1_2026",'{worksheet}'!$M$3:$M$4127,$C31) -> 29064 | J31: =SUMIFS('{worksheet}'!$AE$3:$AE$4127,'{worksheet}'!$AB$3:$AB$4127,"H1_2026",'{worksheet}'!$M$3:$M$4127,$C31) -> 97800169 | K31: =IF(E31=0,"",J31/E31) -> 0.34660166 | L31: =SUMIFS('{worksheet}'!$AD$3:$AD$4127,'{worksheet}'!$AB$3:$AB$4127,"H1_2026",'{worksheet}'!$M$3:$M$4127,$C31,'{worksheet}'!$AF$3:$AF$4127,"Sample")+SUMIFS('{worksheet}'!$AD$3:$AD$4127,'{worksheet}'!$AB$3:$AB$4127,"H1_2026",'{worksheet}'!$M$3:$M$4127,$C31,'{worksheet}'!$AF$3:$AF$4127,"FOC") -> 0 | M31: =IF(AND(D31=0,E31>0),"New in H1'26",IF(AND(D31>0,E31=0),"Exited",IF(G31="","",IF(G31>=0.2,"Growth",IF(G31<=-0.2,"Decline","Stable"))))) -> Growth
A32: 7 | B32: Pyunkang Yul | C32: 편강율 | D32: =SUMIFS('{worksheet}'!$AC$3:$AC$4127,'{worksheet}'!$AB$3:$AB$4127,"H1_2025",'{worksheet}'!$M$3:$M$4127,$C32) -> 2.7657695e+08 | E32: =SUMIFS('{worksheet}'!$AC$3:$AC$4127,'{worksheet}'!$AB$3:$AB$4127,"H1_2026",'{worksheet}'!$M$3:$M$4127,$C32) -> 2.7213084e+08 | F32: =E32-D32 -> -4446108.3 | G32: =IF(D32=0,"",E32/D32-1) -> -0.016075484 | H32: =SUMIFS('{worksheet}'!$AD$3:$AD$4127,'{worksheet}'!$AB$3:$AB$4127,"H1_2025",'{worksheet}'!$M$3:$M$4127,$C32) -> 178311 | I32: =SUMIFS('{worksheet}'!$AD$3:$AD$4127,'{worksheet}'!$AB$3:$AB$4127,"H1_2026",'{worksheet}'!$M$3:$M$4127,$C32) -> 38318 | J32: =SUMIFS('{worksheet}'!$AE$3:$AE$4127,'{worksheet}'!$AB$3:$AB$4127,"H1_2026",'{worksheet}'!$M$3:$M$4127,$C32) -> 52983862 | K32: =IF(E32=0,"",J32/E32) -> 0.19469996 | L32: =SUMIFS('{worksheet}'!$AD$3:$AD$4127,'{worksheet}'!$AB$3:$AB$4127,"H1_2026",'{worksheet}'!$M$3:$M$4127,$C32,'{worksheet}'!$AF$3:$AF$4127,"Sample")+SUMIFS('{worksheet}'!$AD$3:$AD$4127,'{worksheet}'!$AB$3:$AB$4127,"H1_2026",'{worksheet}'!$M$3:$M$4127,$C32,'{worksheet}'!$AF$3:$AF$4127,"FOC") -> 3750 | M32: =IF(AND(D32=0,E32>0),"New in H1'26",IF(AND(D32>0,E32=0),"Exited",IF(G32="","",IF(G32>=0.2,"Growth",IF(G32<=-0.2,"Decline","Stable"))))) -> Stable
A33: 8 | B33: BIODANCE | C33: 바이오던스 | D33: =SUMIFS('{worksheet}'!$AC$3:$AC$4127,'{worksheet}'!$AB$3:$AB$4127,"H1_2025",'{worksheet}'!$M$3:$M$4127,$C33) -> 63799921 | E33: =SUMIFS('{worksheet}'!$AC$3:$AC$4127,'{worksheet}'!$AB$3:$AB$4127,"H1_2026",'{worksheet}'!$M$3:$M$4127,$C33) -> 2.5165444e+08 | F33: =E33-D33 -> 1.8785452e+08 | G33: =IF(D33=0,"",E33/D33-1) -> 2.9444318 | H33: =SUMIFS('{worksheet}'!$AD$3:$AD$4127,'{worksheet}'!$AB$3:$AB$4127,"H1_2025",'{worksheet}'!$M$3:$M$4127,$C33) -> 5558 | I33: =SUMIFS('{worksheet}'!$AD$3:$AD$4127,'{worksheet}'!$AB$3:$AB$4127,"H1_2026",'{worksheet}'!$M$3:$M$4127,$C33) -> 21824 | J33: =SUMIFS('{worksheet}'!$AE$3:$AE$4127,'{worksheet}'!$AB$3:$AB$4127,"H1_2026",'{worksheet}'!$M$3:$M$4127,$C33) -> 1.1303176e+08 | K33: =IF(E33=0,"",J33/E33) -> 0.44915464 | L33: =SUMIFS('{worksheet}'!$AD$3:$AD$4127,'{worksheet}'!$AB$3:$AB$4127,"H1_2026",'{worksheet}'!$M$3:$M$4127,$C33,'{worksheet}'!$AF$3:$AF$4127,"Sample")+SUMIFS('{worksheet}'!$AD$3:$AD$4127,'{worksheet}'!$AB$3:$AB$4127,"H1_2026",'{worksheet}'!$M$3:$M$4127,$C33,'{worksheet}'!$AF$3:$AF$4127,"FOC") -> 0 | M33: =IF(AND(D33=0,E33>0),"New in H1'26",IF(AND(D33>0,E33=0),"Exited",IF(G33="","",IF(G33>=0.2,"Growth",IF(G33<=-0.2,"Decline","Stable"))))) -> Growth
A34: 9 | B34: Arencia | C34: 아렌시아 | D34: =SUMIFS('{worksheet}'!$AC$3:$AC$4127,'{worksheet}'!$AB$3:$AB$4127,"H1_2025",'{worksheet}'!$M$3:$M$4127,$C34) -> 0 | E34: =SUMIFS('{worksheet}'!$AC$3:$AC$4127,'{worksheet}'!$AB$3:$AB$4127,"H1_2026",'{worksheet}'!$M$3:$M$4127,$C34) -> 1.5960145e+08 | F34: =E34-D34 -> 1.5960145e+08 | G34: =IF(D34=0,"",E34/D34-1) | H34: =SUMIFS('{worksheet}'!$AD$3:$AD$4127,'{worksheet}'!$AB$3:$AB$4127,"H1_2025",'{worksheet}'!$M$3:$M$4127,$C34) -> 0 | I34: =SUMIFS('{worksheet}'!$AD$3:$AD$4127,'{worksheet}'!$AB$3:$AB$4127,"H1_2026",'{worksheet}'!$M$3:$M$4127,$C34) -> 14702 | J34: =SUMIFS('{worksheet}'!$AE$3:$AE$4127,'{worksheet}'!$AB$3:$AB$4127,"H1_2026",'{worksheet}'!$M$3:$M$4127,$C34) -> 53993666 | K34: =IF(E34=0,"",J34/E34) -> 0.3383031 | L34: =SUMIFS('{worksheet}'!$AD$3:$AD$4127,'{worksheet}'!$AB$3:$AB$4127,"H1_2026",'{worksheet}'!$M$3:$M$4127,$C34,'{worksheet}'!$AF$3:$AF$4127,"Sample")+SUMIFS('{worksheet}'!$AD$3:$AD$4127,'{worksheet}'!$AB$3:$AB$4127,"H1_2026",'{worksheet}'!$M$3:$M$4127,$C34,'{worksheet}'!$AF$3:$AF$4127,"FOC") -> 0 | M34: =IF(AND(D34=0,E34>0),"New in H1'26",IF(AND(D34>0,E34=0),"Exited",IF(G34="","",IF(G34>=0.2,"Growth",IF(G34<=-0.2,"Decline","Stable"))))) -> New in H1'26
A35: 10 | B35: Dr.Rejuol | C35: 닥터 리쥬올 | D35: =SUMIFS('{worksheet}'!$AC$3:$AC$4127,'{worksheet}'!$AB$3:$AB$4127,"H1_2025",'{worksheet}'!$M$3:$M$4127,$C35) -> 0 | E35: =SUMIFS('{worksheet}'!$AC$3:$AC$4127,'{worksheet}'!$AB$3:$AB$4127,"H1_2026",'{worksheet}'!$M$3:$M$4127,$C35) -> 1.3667044e+08 | F35: =E35-D35 -> 1.3667044e+08 | G35: =IF(D35=0,"",E35/D35-1) | H35: =SUMIFS('{worksheet}'!$AD$3:$AD$4127,'{worksheet}'!$AB$3:$AB$4127,"H1_2025",'{worksheet}'!$M$3:$M$4127,$C35) -> 0 | I35: =SUMIFS('{worksheet}'!$AD$3:$AD$4127,'{worksheet}'!$AB$3:$AB$4127,"H1_2026",'{worksheet}'!$M$3:$M$4127,$C35) -> 5628 | J35: =SUMIFS('{worksheet}'!$AE$3:$AE$4127,'{worksheet}'!$AB$3:$AB$4127,"H1_2026",'{worksheet}'!$M$3:$M$4127,$C35) -> 43924343 | K35: =IF(E35=0,"",J35/E35) -> 0.32138875 | L35: =SUMIFS('{worksheet}'!$AD$3:$AD$4127,'{worksheet}'!$AB$3:$AB$4127,"H1_2026",'{worksheet}'!$M$3:$M$4127,$C35,'{worksheet}'!$AF$3:$AF$4127,"Sample")+SUMIFS('{worksheet}'!$AD$3:$AD$4127,'{worksheet}'!$AB$3:$AB$4127,"H1_2026",'{worksheet}'!$M$3:$M$4127,$C35,'{worksheet}'!$AF$3:$AF$4127,"FOC") -> 588 | M35: =IF(AND(D35=0,E35>0),"New in H1'26",IF(AND(D35>0,E35=0),"Exited",IF(G35="","",IF(G35>=0.2,"Growth",IF(G35<=-0.2,"Decline","Stable"))))) -> New in H1'26
A36: 11 | B36: Heimish | C36: 헤이미쉬 | D36: =SUMIFS('{worksheet}'!$AC$3:$AC$4127,'{worksheet}'!$AB$3:$AB$4127,"H1_2025",'{worksheet}'!$M$3:$M$4127,$C36) -> 66711998 | E36: =SUMIFS('{worksheet}'!$AC$3:$AC$4127,'{worksheet}'!$AB$3:$AB$4127,"H1_2026",'{worksheet}'!$M$3:$M$4127,$C36) -> 80111800 | F36: =E36-D36 -> 13399802 | G36: =IF(D36=0,"",E36/D36-1) -> 0.20086045 | H36: =SUMIFS('{worksheet}'!$AD$3:$AD$4127,'{worksheet}'!$AB$3:$AB$4127,"H1_2025",'{worksheet}'!$M$3:$M$4127,$C36) -> 18708 | I36: =SUMIFS('{worksheet}'!$AD$3:$AD$4127,'{worksheet}'!$AB$3:$AB$4127,"H1_2026",'{worksheet}'!$M$3:$M$4127,$C36) -> 10915 | J36: =SUMIFS('{worksheet}'!$AE$3:$AE$4127,'{worksheet}'!$AB$3:$AB$4127,"H1_2026",'{worksheet}'!$M$3:$M$4127,$C36) -> 20259208 | K36: =IF(E36=0,"",J36/E36) -> 0.25288669 | L36: =SUMIFS('{worksheet}'!$AD$3:$AD$4127,'{worksheet}'!$AB$3:$AB$4127,"H1_2026",'{worksheet}'!$M$3:$M$4127,$C36,'{worksheet}'!$AF$3:$AF$4127,"Sample")+SUMIFS('{worksheet}'!$AD$3:$AD$4127,'{worksheet}'!$AB$3:$AB$4127,"H1_2026",'{worksheet}'!$M$3:$M$4127,$C36,'{worksheet}'!$AF$3:$AF$4127,"FOC") -> 0 | M36: =IF(AND(D36=0,E36>0),"New in H1'26",IF(AND(D36>0,E36=0),"Exited",IF(G36="","",IF(G36>=0.2,"Growth",IF(G36<=-0.2,"Decline","Stable"))))) -> Growth
A37: 12 | B37: Dr.Elsia | C37: 닥터엘시아 | D37: =SUMIFS('{worksheet}'!$AC$3:$AC$4127,'{worksheet}'!$AB$3:$AB$4127,"H1_2025",'{worksheet}'!$M$3:$M$4127,$C37) -> 7.5612225e+08 | E37: =SUMIFS('{worksheet}'!$AC$3:$AC$4127,'{worksheet}'!$AB$3:$AB$4127,"H1_2026",'{worksheet}'!$M$3:$M$4127,$C37) -> 76675686 | F37: =E37-D37 -> -6.7944656e+08 | G37: =IF(D37=0,"",E37/D37-1) -> -0.89859353 | H37: =SUMIFS('{worksheet}'!$AD$3:$AD$4127,'{worksheet}'!$AB$3:$AB$4127,"H1_2025",'{worksheet}'!$M$3:$M$4127,$C37) -> 57560 | I37: =SUMIFS('{worksheet}'!$AD$3:$AD$4127,'{worksheet}'!$AB$3:$AB$4127,"H1_2026",'{worksheet}'!$M$3:$M$4127,$C37) -> 6000 | J37: =SUMIFS('{worksheet}'!$AE$3:$AE$4127,'{worksheet}'!$AB$3:$AB$4127,"H1_2026",'{worksheet}'!$M$3:$M$4127,$C37) -> 18429186 | K37: =IF(E37=0,"",J37/E37) -> 0.24035241 | L37: =SUMIFS('{worksheet}'!$AD$3:$AD$4127,'{worksheet}'!$AB$3:$AB$4127,"H1_2026",'{worksheet}'!$M$3:$M$4127,$C37,'{worksheet}'!$AF$3:$AF$4127,"Sample")+SUMIFS('{worksheet}'!$AD$3:$AD$4127,'{worksheet}'!$AB$3:$AB$4127,"H1_2026",'{worksheet}'!$M$3:$M$4127,$C37,'{worksheet}'!$AF$3:$AF$4127,"FOC") -> 0 | M37: =IF(AND(D37=0,E37>0),"New in H1'26",IF(AND(D37>0,E37=0),"Exited",IF(G37="","",IF(G37>=0.2,"Growth",IF(G37<=-0.2,"Decline","Stable"))))) -> Decline
... A117: 92 | B117: Dr.Suracle | C117: 닥터슈라클 | D117: =SUMIFS('{worksheet}'!$AC$3:$AC$4127,'{worksheet}'!$AB$3:$AB$4127,"H1_2025",'{worksheet}'!$M$3:$M$4127,$C117) -> 0 | E117: =SUMIFS('{worksheet}'!$AC$3:$AC$4127,'{worksheet}'!$AB$3:$AB$4127,"H1_2026",'{worksheet}'!$M$3:$M$4127,$C117) -> 0 | F117: =E117-D117 -> 0 | G117: =IF(D117=0,"",E117/D117-1) | H117: =SUMIFS('{worksheet}'!$AD$3:$AD$4127,'{worksheet}'!$AB$3:$AB$4127,"H1_2025",'{worksheet}'!$M$3:$M$4127,$C117) -> 12 | I117: =SUMIFS('{worksheet}'!$AD$3:$AD$4127,'{worksheet}'!$AB$3:$AB$4127,"H1_2026",'{worksheet}'!$M$3:$M$4127,$C117) -> 0 | J117: =SUMIFS('{worksheet}'!$AE$3:$AE$4127,'{worksheet}'!$AB$3:$AB$4127,"H1_2026",'{worksheet}'!$M$3:$M$4127,$C117) -> 0 | K117: =IF(E117=0,"",J117/E117) | L117: =SUMIFS('{worksheet}'!$AD$3:$AD$4127,'{worksheet}'!$AB$3:$AB$4127,"H1_2026",'{worksheet}'!$M$3:$M$4127,$C117,'{worksheet}'!$AF$3:$AF$4127,"Sample")+SUMIFS('{worksheet}'!$AD$3:$AD$4127,'{worksheet}'!$AB$3:$AB$4127,"H1_2026",'{worksheet}'!$M$3:$M$4127,$C117,'{worksheet}'!$AF$3:$AF$4127,"FOC") -> 0 | M117: =IF(AND(D117=0,E117>0),"New in H1'26",IF(AND(D117>0,E117=0),"Exited",IF(G117="","",IF(G117>=0.2,"Growth",IF(G117<=-0.2,"Decline","Stable")))))
A120: [Chart data — Top 10 brands] | E120: [Chart data — Biggest movers by Δ Revenue]
A121: Brand | B121: H1 2025 | C121: H1 2026 | E121: Brand | F121: Δ Revenue
A122: =B26 -> Beauty of Joseon | B122: =D26 -> 2.1048138e+09 | C122: =E26 -> 2.2701934e+09 | E122: =INDEX($B$26:$B$117,MATCH(LARGE($F$26:$F$117,ROW()-121),$F$26:$F$117,0)) -> medicube | F122: =LARGE($F$26:$F$117,ROW()-121) -> 1.5884358e+09
A123: =B27 -> medicube | B123: =D27 -> 3.9262294e+08 | C123: =E27 -> 1.9810588e+09 | E123: =INDEX($B$26:$B$117,MATCH(LARGE($F$26:$F$117,ROW()-121),$F$26:$F$117,0)) -> Anua | F123: =LARGE($F$26:$F$117,ROW()-121) -> 1.4155701e+09
A124: =B28 -> Anua | B124: =D28 -> 20961 | C124: =E28 -> 1.4155911e+09 | E124: =INDEX($B$26:$B$117,MATCH(LARGE($F$26:$F$117,ROW()-121),$F$26:$F$117,0)) -> COSRX | F124: =LARGE($F$26:$F$117,ROW()-121) -> 3.3833846e+08
A125: =B29 -> COSRX | B125: =D29 -> 97689804 | C125: =E29 -> 4.3602826e+08 | E125: =INDEX($B$26:$B$117,MATCH(LARGE($F$26:$F$117,ROW()-121),$F$26:$F$117,0)) -> Round Lab | F125: =LARGE($F$26:$F$117,ROW()-121) -> 2.6718993e+08
A126: =B30 -> Round Lab | B126: =D30 -> 48847212 | C126: =E30 -> 3.1603714e+08 | E126: =INDEX($B$26:$B$117,MATCH(LARGE($F$26:$F$117,ROW()-121),$F$26:$F$117,0)) -> Celimax | F126: =LARGE($F$26:$F$117,ROW()-121) -> 2.0781461e+08
A127: =B31 -> Celimax | B127: =D31 -> 74354178 | C127: =E31 -> 2.8216878e+08 | E127: =INDEX($B$26:$B$117,MATCH(LARGE($F$26:$F$117,ROW()-121),$F$26:$F$117,0)) -> BIODANCE | F127: =LARGE($F$26:$F$117,ROW()-121) -> 1.8785452e+08
A128: =B32 -> Pyunkang Yul | B128: =D32 -> 2.7657695e+08 | C128: =E32 -> 2.7213084e+08 | E128: =INDEX($B$26:$B$117,MATCH(SMALL($F$26:$F$117,ROW()-127),$F$26:$F$117,0)) -> Dr.Elsia | F128: =SMALL($F$26:$F$117,ROW()-127) -> -6.7944656e+08
A129: =B33 -> BIODANCE | B129: =D33 -> 63799921 | C129: =E33 -> 2.5165444e+08 | E129: =INDEX($B$26:$B$117,MATCH(SMALL($F$26:$F$117,ROW()-127),$F$26:$F$117,0)) -> VT Cosmetics | F129: =SMALL($F$26:$F$117,ROW()-127) -> -87346885
A130: =B34 -> Arencia | B130: =D34 -> 0 | C130: =E34 -> 1.5960145e+08 | E130: =INDEX($B$26:$B$117,MATCH(SMALL($F$26:$F$117,ROW()-127),$F$26:$F$117,0)) -> JUMISO | F130: =SMALL($F$26:$F$117,ROW()-127) -> -71557802
A131: =B35 -> Dr.Rejuol | B131: =D35 -> 0 | C131: =E35 -> 1.3667044e+08 | E131: =INDEX($B$26:$B$117,MATCH(SMALL($F$26:$F$117,ROW()-127),$F$26:$F$117,0)) -> iUNIK | F131: =SMALL($F$26:$F$117,ROW()-127) -> -51671049
E132: =INDEX($B$26:$B$117,MATCH(SMALL($F$26:$F$117,ROW()-127),$F$26:$F$117,0)) -> Marie en May | F132: =SMALL($F$26:$F$117,ROW()-127) -> -28934461

Sheet Meeting Prep
A1: H1 2026 REVIEW — MEETING PREP: WHAT YOU MUST KNOW
A2: MOARS (Netherlands) · Jan–Jun 2026 vs Jan–Jun 2025 · Revenue in KRW (converted amount) · Source: {worksheet} → see 'H1 Analysis' for detail
A4: 1. HEADLINE
A5: ="• Total revenue grew to "&TEXT('H1 Analysis'!C6/1000000,"#,##0")&"M KRW — "&TEXT('H1 Analysis'!E6,"+0.0%;-0.0%")&" YoY (from "&TEXT('H1 Analysis'!B6/1000000,"#,##0")&"M). This is the single biggest talking point." -> • Total revenue grew to 8,153M KRW — +80.3% YoY (from 4,523M). This is the single biggest talking point.
A6: ="• Gross profit "&TEXT('H1 Analysis'!C7/1000000,"#,##0")&"M KRW ("&TEXT('H1 Analysis'!E7,"+0.0%")&"); gross margin improved to "&TEXT('H1 Analysis'!C8,"0.0%")&" ("&TEXT('H1 Analysis'!D8*100,"+0.0;-0.0")&"pp) — growth was profitable, not just top-line." -> • Gross profit 1,893M KRW (+109.4%); gross margin improved to 23.2% (+3.2pp) — growth was profitable, not just top-line.
A7: ="• Units sold FELL "&TEXT(-'H1 Analysis'!E9,"0.0%")&" to "&TEXT('H1 Analysis'!C9,"#,##0")&" units while revenue rose 80% — a clear mix shift to higher-value brands/SKUs (higher average selling price). Expect a question on this." -> • Units sold FELL 14.1% to 807,407 units while revenue rose 80% — a clear mix shift to higher-value brands/SKUs (higher average selling price). Expect a question on this.
A8: ="• Order lines "&TEXT('H1 Analysis'!E10,"+0.0%")&" ("&'H1 Analysis'!B10&"→"&'H1 Analysis'!C10&"); active brands "&'H1 Analysis'!B11&"→"&'H1 Analysis'!C11&". Broader, more frequent ordering." -> • Order lines +65.0% (949→1566); active brands 59→63. Broader, more frequent ordering.
A10: 2. WHAT'S DRIVING GROWTH
A11: ="• medicube is the #1 growth engine: +"&TEXT('H1 Analysis'!F27/1000000,"#,##0")&"M KRW ("&TEXT('H1 Analysis'!G27,"+0%")&"), now the #2 brand overall at "&TEXT('H1 Analysis'!E27/1000000,"#,##0")&"M." -> • medicube is the #1 growth engine: +1,588M KRW (+405%), now the #2 brand overall at 1,981M.
A12: ="• Anua effectively launched as a full-sales brand: "&TEXT('H1 Analysis'!E28/1000000,"#,##0")&"M KRW in H1'26 vs virtually nil in H1'25 (sample-only prior). Now the #3 brand." -> • Anua effectively launched as a full-sales brand: 1,416M KRW in H1'26 vs virtually nil in H1'25 (sample-only prior). Now the #3 brand.
A13: • Second wave of breakout brands (all +250% or more): COSRX, Round Lab, BIODANCE, and Celimax (Celimax also carries the best margin among leaders at ~35%).
A14: • New brands introduced in H1'26 contributing real revenue: Arencia (~160M) and Dr.Rejuol (~137M), plus smaller additions (Lagom, G9SKIN).
A15: ="• Beauty of Joseon remains the anchor (#1 at "&TEXT('H1 Analysis'!E26/1000000,"#,##0")&"M) but growth is nearly flat ("&TEXT('H1 Analysis'!G26,"+0.0%")&"). It is holding share, not driving growth — watch for maturity/saturation." -> • Beauty of Joseon remains the anchor (#1 at 2,270M) but growth is nearly flat (+7.9%). It is holding share, not driving growth — watch for maturity/saturation.
A17: 3. RISKS & WATCH-OUTS
A18: ="• Revenue concentration is HIGH: top 3 brands (Beauty of Joseon, medicube, Anua) = "&TEXT(SUM('H1 Analysis'!E26:E28)/'H1 Analysis'!C6,"0%")&" of H1'26 revenue. A stumble in any one materially hits the total." -> • Revenue concentration is HIGH: top 3 brands (Beauty of Joseon, medicube, Anua) = 70% of H1'26 revenue. A stumble in any one materially hits the total.
A19: ="• Dr.Elsia collapsed: "&TEXT(INDEX('H1 Analysis'!$D$26:$D$117,MATCH("Dr.Elsia",'H1 Analysis'!$B$26:$B$117,0))/1000000,"#,##0")&"M → "&TEXT(INDEX('H1 Analysis'!$E$26:$E$117,MATCH("Dr.Elsia",'H1 Analysis'!$B$26:$B$117,0))/1000000,"#,##0")&"M KRW. It was the #2 brand in H1'25 — understand why (delisting? stock? demand?) before the meeting." -> • Dr.Elsia collapsed: 756M → 77M KRW. It was the #2 brand in H1'25 — understand why (delisting? stock? demand?) before the meeting.
A20: • Steep decliners & exits: VT Cosmetics -98%; brands that went to zero in H1'26 include JUMISO (~72M in H1'25), Axis-Y (~29M), MISSHA, W.DRESSROOM, Have Blue. Confirm these were intentional (discontinued) vs. lost business.
A21: ="• April was the only down month: "&TEXT('H1 Analysis'!D19,"0.0%")&" YoY. Every other month grew (Jan +384%, Jun +194%). Have an explanation ready for the April dip." -> • April was the only down month: -18.5% YoY. Every other month grew (Jan +384%, Jun +194%). Have an explanation ready for the April dip.
A22: • Growth leans on young/volatile brands (medicube, Anua, COSRX). High growth % comes off small H1'25 bases — sustainability into H2 is the key unknown.
A24: 4. FOC & SAMPLING
A25: ="• Free/promotional units cut sharply: "&TEXT('H1 Analysis'!B12,"#,##0")&" → "&TEXT('H1 Analysis'!C12,"#,##0")&" units ("&TEXT('H1 Analysis'!E12,"0.0%")&"). Far less product given away per KRW of sales." -> • Free/promotional units cut sharply: 36,542 → 7,223 units (-80.2%). Far less product given away per KRW of sales.
A26: • The MIX of free goods changed: H1'25 was almost entirely product samples (36,542 units, no FOC). H1'26 samples fell to 435 units, replaced by targeted FOC trade incentives (6,788 units).
A27: • H1'26 FOC (sales-incentive) units are concentrated in just 3 brands: Pyunkang Yul 3,750, Klavuu 2,550, Dr.Rejuol 488. Worth confirming the ROI / intent of these incentives.
A29: 5. QUESTIONS / TALKING POINTS FOR H2
A30: • Can medicube, Anua, COSRX, Round Lab, BIODANCE sustain momentum, or is this pipeline fill / one-off stocking?
A31: • Is the Dr.Elsia decline recoverable, and what replaces its H1'25 volume?
A32: • Given units down but revenue up — is this deliberate premiumization, or price/FX effects we should validate?
A33: • Reduce concentration risk: which mid-tier brands (Celimax, BIODANCE, Round Lab) should we push in H2?
A34: • H2'25 (Jul–Dec) was strong in the source data — set H2'26 targets against that comparable, not against H1.
A36: Data notes: All shipments are to one destination (Netherlands / MOARS). Revenue uses converted amount (환산금액, KRW); source amounts were stored as text and converted via helper columns AA:AF on {worksheet}. English brand names are best-effort mappings of the Korean source names (kept in 'H1 Analysis' col C for traceability).

Sheet 요약·특이점 (KR)
B1: MOARS 상반기 매출 요약 · 특이점 (2025 vs 2026)
B2: 고객사: MOARS (네덜란드) · 기간: 1~6월 · 매출: 환산금액(KRW) · 출처: {worksheet} · 상세: 'H1 Analysis' 참고
B4: 총매출 (H1'26, KRW) | F4: 매출총이익 (KRW) | J4: 이익률
B5: ='H1 Analysis'!C6 -> 8.1526898e+09 | F5: ='H1 Analysis'!C7 -> 1.8934963e+09 | J5: ='H1 Analysis'!C8 -> 0.23225418
B6: ="▲ "&TEXT('H1 Analysis'!E6,"0.0%")&" YoY" -> ▲ 80.3% YoY | F6: ="▲ "&TEXT('H1 Analysis'!E7,"0.0%")&" YoY" -> ▲ 109.4% YoY | J6: ="▲ "&TEXT('H1 Analysis'!D8,"0.0%")&"p" -> ▲ 3.2%p
B8: 판매수량 (개) | F8: 거래 건수 | J8: 무상수량 (샘플+FOC)
B9: ='H1 Analysis'!C9 -> 807407 | F9: ='H1 Analysis'!C10 -> 1566 | J9: ='H1 Analysis'!C12 -> 7223
B10: ="▼ "&TEXT('H1 Analysis'!E9,"0.0%")&" YoY" -> ▼ -14.1% YoY | F10: ="▲ "&TEXT('H1 Analysis'!E10,"0.0%")&" YoY" -> ▲ 65.0% YoY | J10: ="▼ "&TEXT('H1 Analysis'!E12,"0.0%")&" YoY" -> ▼ -80.2% YoY
B62: [차트 데이터 — H1'26 매출 구성]
B63: 브랜드 | C63: H1'26 매출
B64: ='H1 Analysis'!B26 -> Beauty of Joseon | C64: ='H1 Analysis'!E26 -> 2.2701934e+09
B65: ='H1 Analysis'!B27 -> medicube | C65: ='H1 Analysis'!E27 -> 1.9810588e+09
B66: ='H1 Analysis'!B28 -> Anua | C66: ='H1 Analysis'!E28 -> 1.4155911e+09
B67: ='H1 Analysis'!B29 -> COSRX | C67: ='H1 Analysis'!E29 -> 4.3602826e+08
B68: ='H1 Analysis'!B30 -> Round Lab | C68: ='H1 Analysis'!E30 -> 3.1603714e+08
B69: ='H1 Analysis'!B31 -> Celimax | C69: ='H1 Analysis'!E31 -> 2.8216878e+08
B70: 기타 (Others) | C70: ='H1 Analysis'!C6-SUM('H1 Analysis'!E26:E31) -> 1.4516124e+09
